Workbook

Sheet 0. Investment Memo
B1: INVESTMENT COMMITTEE MEMORANDUM
B2: V3 Grand Madurai - 4-Star Boutique Business Hotel
B3: Chinthamani Ring Road, Madurai | ₹43 Crore Investment | February 2026
B5: RECOMMENDATION | C5: ⚠️ CONDITIONAL APPROVAL - Subject to Risk Mitigation & Lite Alternative Review
B7: ⚠️ MINIMAL IRR MARGIN | C7: HIGH | D7: IRR 17.8% vs 17.5% hurdle = 0.3 pp. Any variance fails hurdle. Requires: Strict cost controls, daily revenue mgmt, consider 3-star Lite.
B8: ⚠️ OCCUPANCY RAMP RISK | C8: HIGH | D8: Model assumes 40% Y1, 60% Y2. New hotel may achieve only 25-35% Y1, extending payback >10 years. Requires: Pre-opening sales, anchor contracts.
B9: ⚠️ AMENITY-DEMAND MISMATCH | C9: MEDIUM-HIGH | D9: 4-star amenities may exceed Madurai willingness-to-pay. Requires: Market validation, consider 3-star Lite (₹28-30 Cr CAPEX, better fit).
B10: Risk Rating | C10: HIGH - Minimal IRR Margin (0.3 pp over hurdle)
B11: ⚠️ CRITICAL: MODEL RESTRUCTURED WITH REALISTIC ASSUMPTIONS
B12: Metric | C12: Original Model | D12: Restructured Model | E12: Impact
B13: Hurdle Rate | C13: 17.5% | D13: 17.5% | E13: +5.5 pp (proper WACC)
B14: Year 1 Occupancy | C14: 65% | D14: 40% | E14: -25 pp (realistic ramp)
B15: NPV @ Hurdle | C15: ₹0.69 Cr | D15: ₹0.69 Cr | E15: -95.7% collapse
B16: IRR Margin | C16: 5.8 pp over hurdle | D16: 0.3 pp over hurdle | E16: No safety margin
B17: ⚠️ PROJECT NOW MARGINALLY VIABLE: IRR 17.8% vs 17.5% hurdle = 0.3 pp margin. Any adverse variance will fail hurdle.
B20: KEY INVESTMENT METRICS
B21: Total Investment | C21: ₹43.0 Crore | F21: Expected IRR (Base) | G21: 17.8%
B22: • Phase 1 (55 keys) | C22: ₹35.7 Cr | F22: NPV @ 17.5% | G22: ₹0.69 Cr
B23: • Phase 2 (+17 keys) | C23: ₹7.3 Cr | F23: Payback Period | G23: 9.2 years
B24: Equity:Debt Ratio | C24: 60:40 | F24: Return Multiple | G24: 2.71x
B25: Project Timeline | C25: 28 months to Phase 1 opening | F25: Exit Value (Yr 10) | G25: ₹98.5 Cr @ 12x EBITDA
B28: CAPITAL STRUCTURE OPTIONS
B30: Financing Option | C30: Debt Amount | D30: Equity Required | E30: IRR | F30: NPV @ 17.5% | G30: Risk Level | H30: Recommendation
B31: 40% Debt (Current) | C31: ₹17.2 Cr | D31: ₹25.8 Cr | E31: 0.209 | F31: ₹0.92 Cr | G31: Moderate | H31: ⚠️ Marginal viability
B32: 30% Debt (Recommended) | C32: ₹12.9 Cr | D32: ₹30.1 Cr | E32: 0.201 | F32: ₹0.75 Cr | G32: Low-Moderate | H32: ✅ BALANCED RISK/RETURN
B33: 20% Debt (Conservative) | C33: ₹8.6 Cr | D33: ₹34.4 Cr | E33: 0.194 | F33: ₹0.58 Cr | G33: Low | H33: Minimum risk
B35: Board Recommendation: 30% Debt Structure offers optimal balance with IRR of 20.1% (8.1% above hurdle) while improving debt service coverage to 2.8x and requiring only ₹4.3 Cr additional equity vs current structure.
B40: INVESTMENT HIGHLIGHTS
B41: • Strategic Location
B42: Adjacent to 3 major hospitals (1,100+ beds), no competing 4-star hotels within 5km radius, medical tourism hub
B43: • Strong Anchor Partnerships
B44: Confirmed MOUs delivering 13% occupancy floor from day one (Vikram Hospital, Hannah Joseph Hospital, Aravind Eye)
B45: • Robust Financial Returns
B46: ₹0.69 Cr
B47: • Phased Growth Strategy
B48: 55 keys in Phase 1 de-risks execution, Phase 2 (+17 keys) triggered only after 8-point validation at Month 36
B49: • Owner-Operator Model
B50: No franchise fees (saves ₹0.3-1.8 Cr/year), full operational control, 40.4% EBITDA margin vs 27-35% with brands
B53: KEY RISKS & MITIGATIONS
B54: Risk | C54: Impact | D54: Mitigation
B55: Market/Demand | C55: High | D55: Anchor MOUs provide 13% occupancy floor, diversified demand sources (medical + corporate + leisure)
B56: Competition | C56: Medium | D56: No 4-star supply within 5km, established relationships before new entrants arrive
B57: Construction Delay | C57: Medium | D57: Experienced contractor, 8% contingency buffer, phased approach allows learning
B58: Cost Overrun | C58: Medium | D58: Fixed-price contracts for 70% of CAPEX, 8% contingency reserve (₹3.4 Cr)
B59: Phase 2 Execution | C59: Low | D59: 8-point decision gate at Month 36, Phase 2 standalone IRR 22%, can optimize at Phase 1 if needed
B63: SCENARIO ANALYSIS
B64: Scenario | C64: Probability | D64: IRR | E64: NPV (₹ Cr) | F64: Payback | G64: Key Assumption
B65: Bear Case | C65: 20% | D65: 14.3% | E65: ₹7.1 | F65: 9.2 yrs | G65: 63% occupancy, Phase 2 not triggered
B66: Base Case | C66: 60% | D66: 17.8% | E66: ₹0.69 Cr | F66: 7.8 yrs | G66: 78% occupancy, Phase 2 at Month 43
B67: Bull Case | C67: 20% | D67: 22.9% | E67: ₹27.8 | F67: 6.4 yrs | G67: 82% occupancy, strong corporate demand
B68: Expected (Wtd.) | C68: 100% | D68: 18.3% | E68: ₹16.9 | F68: 7.7 yrs | G68: Probability-weighted average
B70: COMPREHENSIVE RISK DISCLOSURE & MITIGATION STRATEGIES
B72: 1. OCCUPANCY RAMP-UP RISK | F72: Risk Level: | G72: HIGH
B73: Description: | C73: Model assumes 40% Year 1 occupancy. Actual hotel ramps in Tier-II cities average 25-35% Y1. Lower occupancy extends payback from 9.2 years to 11+ years and pushes NPV negative.
B74: Financial Impact: | C74: Each 5 pp occupancy shortfall reduces Year 1 revenue by ₹0.92 Cr and NPV by ₹1.2-1.5 Cr
B75: Mitigation Strategies:
C76: • Pre-opening sales: Secure 60-70% MOU coverage (medical anchors, corporate contracts) before launch
C77: • Phased staffing: Defer 25% of hires until Month 3 based on booking trends
C78: • Dynamic pricing: Implement aggressive promotional ADR (₹2,800-3,200) for first 90 days
C79: • OTA visibility: Pre-launch listings on 8+ platforms with introductory discounts
B81: 2. AMENITY-DEMAND MISMATCH RISK | F81: Risk Level: | G81: MEDIUM-HIGH
B82: Description: | C82: 4-star amenities may exceed Madurai market willingness-to-pay. Guest surveys show ₹3,200-3,800 ADR preference vs. model's ₹5,000 stabilized ADR. Under-utilization of premium amenities reduces EBITDA margin.
B83: Financial Impact: | C83: ADR 10% below assumption (₹4,500 vs ₹5,000) reduces stabilized EBITDA by ₹1.8 Cr/year and IRR from 17.8% to 15.2% (fails hurdle)
B84: Mitigation Strategies:
C85: • Market validation: 8-week survey of 50+ corporates and 200+ medical tourists on ADR acceptance
C86: • 3-Star Lite Alternative: Pivot to ₹29.5 Cr CAPEX model with ₹3,500 ADR, 19.2% IRR, ₹4.8 Cr NPV (see Sheet 16)
C87: • Modular design: Specify interiors allowing future upgrade (standard fixtures now, luxury retrofit Year 3-5)
C88: • F&B rationalization: Start with bistro/café (vs full restaurant), expand only if demand justifies
B90: 3. TIER-II EXECUTION & OPERATIONAL RISK | F90: Risk Level: | G90: MEDIUM
B91: Description: | C91: Limited availability of experienced hotel management talent in Madurai. Construction cost overruns and delays common in Tier-II cities. Owner-operator model assumes hands-on involvement; absence of professional GM adds execution risk.
B92: Financial Impact: | C92: 6-month construction delay costs ₹0.5 Cr in holding costs and defers revenue. Poor GM execution could depress occupancy by 10-15 pp in Year 1-2
B93: Mitigation Strategies:
C94: • Contractor vetting: Pre-qualify 3+ civil contractors with proven Tier-II hotel experience; fixed-price turnkey contract
C95: • 8% contingency buffer built into CAPEX (₹3.4 Cr) for cost overruns
C96: • Owner training: 6-month hospitality management program (IHM or AHLEI certification) before launch
C97: • Consultant support: Engage hotel opening specialist (₹8-12 L fee) for Month -3 to Month +6
C98: • Backup plan: If owner-operator model fails, pivot to Lemon Tree franchise (IRR ~11.9% vs 15.7% independent)
B100: 4. WACC & DISCOUNT RATE RISK | F100: Risk Level: | G100: MEDIUM
B101: Description: | C101: Model uses 17.5% WACC hurdle (vs prior optimistic 12%). IRR of 17.8% provides only 0.3 pp safety margin. If risk-free rate increases 50 bps or project risk premium rises, WACC could exceed 18%, causing project to fail hurdle.
B102: Financial Impact: | C102: WACC increase to 18.5% pushes NPV to ₹-1.8 Cr (negative). Pre-tax debt cost increase from 11.5% to 12.5% reduces IRR by ~0.8 pp to 17.0%
B103: Mitigation Strategies:
C104: • Interest rate hedge: Lock in 11.5% rate with lender for first 5 years (vs floating MCLR+300 bps)
C105: • Debt structure: Target 30% debt (vs 40%) to reduce interest burden; improves DSCR from 2.0× to 2.8×
C106: • IRR improvement levers: Focus on occupancy outperformance (each 2 pp above 78% adds ~0.5 pp to IRR)
C107: • Lite alternative: 3-star model delivers 19.2% IRR with 1.7 pp buffer above 17.5% hurdle
B109: 5. COMPETITIVE ENTRY RISK | F109: Risk Level: | G109: MEDIUM-LOW
B110: Description: | C110: No existing 4-star hotels within 5 km of site (competitive moat). However, Residency Tower could upgrade, or new branded entrants could enter if medical corridor development accelerates. Loss of first-mover advantage could compress ADR and occupancy.
B111: Financial Impact: | C111: New 4-star competitor within 18 months could depress stabilized occupancy by 8-12 pp and ADR by ₹500-800, reducing IRR to 13-15% range
B112: Mitigation Strategies:
C113: • Speed to market: Fast-track construction to achieve Month 28 launch and capture 24-month first-mover window
C114: • Anchor lock-in: 3-year MOUs with hospitals and corporates (pre-emptive contracts before competitor launch)
C115: • Reputation moat: Target 4.5+ OTA rating by Month 12 to build brand loyalty and referrals
C116: • Phase 2 gate: Hold Phase 2 decision until Month 36 to assess competitive landscape before expanding
B119: RISK SUMMARY MATRIX
B120: Risk Category | C120: Risk Level | D120: NPV Impact Range | E120: Mitigation Cost | F120: Net Risk Rating
B121: Occupancy Ramp | C121: HIGH | D121: ₹-1.2 to -3.5 Cr | E121: ₹0.4 Cr | F121: MEDIUM
B122: Amenity-Demand | C122: MED-HIGH | D122: ₹-0.7 to -8.2 Cr | E122: ₹0.2 Cr | F122: MEDIUM
B123: Tier-II Execution | C123: MEDIUM | D123: ₹-0.5 to -2.0 Cr | E123: ₹0.3 Cr | F123: LOW-MEDIUM
B124: WACC Sensitivity | C124: MEDIUM | D124: ₹-2.5 to -4.0 Cr | E124: ₹0.1 Cr | F124: MEDIUM
B125: Competition | C125: MED-LOW | D125: ₹-1.0 to -2.5 Cr | E125: ₹0 Cr | F125: LOW
...

Sheet 1. Executive Summary
B1: V3 GRAND MADURAI | Investment Committee Presentation | Base Case Analysis
B2: Prepared: 24 February 2026
B4: V3 GRAND MADURAI | J4: Investment Committee | K4: Presentation
B5: Executive Summary · Investment Committee Presentation · 4-Star Boutique Business Hotel · Chinthamani Ring Road, Madurai | K5: Giritharan Chockalingam
B6: ⚠️ RESTRUCTURED MODEL: Base Case · Phased Mode · MARGINAL RETURNS (17.8% IRR vs 17.5% hurdle)
M7: INVESTMENT COMMITTEE SCORECARD
B8: TOTAL INVESTMENT | D8: EXPECTED IRR | F8: NPV @ 12% | H8: PAYBACK | J8: RETURN MULTIPLE
B9: ₹43.0 Crore | D9: 0.178 | F9: ₹15.9 Crore | H9: 7.8 Years | J9: 2.71x | M9: Overall Recommendation: | N9: ✅ STRONG BUY
B10: P1: ₹35.7 Cr · P2: ₹7.3 Cr | D10: Prob.-weighted | Hurdle: 12% | F10: Phased, discounted @ 12% | H10: Cumulative FCF positive | J10: 10-yr exit at 12x EBITDA
M11: Risk Rating: | N11: MODERATE
B12: BOARD HURDLE CRITERIA | E12: ⚠️ CONDITIONAL APPROVAL
B13: NPV @ 17.5% | C13: Hurdle | D13: ₹0.69 Cr | E13: Status | G13: Criterion | H13: Hurdle | I13: Actual | J13: Status | M13: Investment Priority: | N13: Tier 1 - Immediate Approval
B14: IRR > 17.5% (Proper WACC Hurdle) | C14: ⚠️ MARGINAL (9.2 yrs, close to limit) | D14: 0.178 | E14: PASS | G14: Payback < 10 years | H14: 10 yrs | I14: 7.8 yrs | J14: PASS
B15: NPV > ₹0 | C15: ✅ PASS (₹0.69 Cr, barely positive) | D15: ₹15.9 Cr | E15: PASS | G15: Return Multiple > 2.0x | H15: 2.0x | I15: 2.71x | J15: PASS | M15: Metric | N15: Status | O15: Value
B16: Bear IRR > 17.5% | C16: ❌ FAIL (Bear 14.3% < 17.5%) | D16: HIGH - Minimal IRR Margin | E16: PASS | G16: EBITDA Margin > 35% | H16: 0.35 | I16: 0.404 | J16: PASS | M16: IRR vs Hurdle | N16: ✅ | O16: 17.8% vs 12.0%
D17: Tier 2 - Conditional/Defer | M17: NPV Creation | N17: ✅ | O17: ₹15.9 Cr positive
B18: SCENARIO ANALYSIS | M18: Payback Period | N18: ✅ | O18: 7.8 years
C19: Bear Case (20%) | D19: Base Case (60%) | E19: Bull Case (20%) | F19: Expected (Wtd.) | M19: Return Multiple | N19: ✅ | O19: 2.71x
B20: ⚠️ CRITICAL MODEL CHANGES & RISKS
B21: Risk Factor | C21: Impact
B22: 1. Minimal IRR Margin | C22: IRR 17.8% vs 17.5% hurdle = 0.3 pp margin only. Any adverse variance fails hurdle.
B23: 2. NPV Collapse | C23: NPV @ proper hurdle dropped from ₹15.9 Cr to ₹0.69 Cr (-95.7%). Marginal value creation.
B24: 3. Extended Payback | C24: Payback now 9.2 years (was 7.8 yrs) due to realistic 40% Y1 occupancy assumption.
B25: 4. Occupancy Risk | C25: 40% Y1 occupancy assumption still optimistic. Actuals may be 25-35%, extending payback further.
B26: 5. Amenity-Demand Mismatch | C26: 4-star amenities may exceed local WTP. Market validation critical before proceeding.
B32: IRR (10-Year) | C32: 0.143 | D32: 0.178 | E32: 0.229 | F32: 0.183 | M32: Bear Case IRR | N32: ✅ | O32: 14.3% (above hurdle)
B33: NPV @ 12% | C33: ₹7.1 Cr | D33: ₹15.9 Cr | E33: ₹27.8 Cr | F33: ₹16.9 Cr | M33: EBITDA Margin | N33: ✅ | O33: 40.4%
B34: Payback Period | C34: 9.2 years | D34: 7.8 years | E34: 6.4 years | F34: 7.7 years | M34: Anchor Coverage | N34: ✅ | O34: 13% occupancy floor
B35: Return Multiple | C35: 2.1x | D35: 2.71x | E35: 3.4x | F35: 2.74x | M35: Exit Strategy | N35: ✅ | O35: 12x EBITDA (₹98.5 Cr)
B36: Phase 2 Triggered? | C36: No | D36: Yes | E36: Yes | F36: —
M37: KEY RISK ASSESSMENT
B38: 10-YEAR PROJECTION · Base Case, Phased Expansion
B39: ₹ Crore | C39: Year 1 | D39: Year 2 | E39: Year 3 | F39: Year 5 | G39: Year 7 | H39: Year 10 | M39: Risk Category | N39: Impact | O39: Likelihood | P39: Mitigation
B40: Revenue | C40: ₹7.33 | D40: ₹8.73 | E40: ₹10.02 | F40: ₹15.17 | G40: ₹16.73 | H40: ₹19.37 | M40: Market/Occupancy | N40: High | O40: Medium | P40: Anchor MOUs
B41: EBITDA | C41: ₹2.93 | D41: ₹3.53 | E41: ₹4.05 | F41: ₹6.07 | G41: ₹6.88 | H41: ₹8.21 | M41: Competition | N41: Medium | O41: Low | P41: No 4-star in zone
B42: EBITDA Margin | C42: 0.4 | D42: 0.405 | E42: 0.404 | F42: 0.4 | G42: 0.411 | H42: 0.424 | M42: Construction Delay | N42: Medium | O42: Low | P42: Buffer built-in
B43: Occupancy | C43: 0.65 | D43: 0.7 | E43: 0.75 | F43: 0.78 | G43: 0.78 | H43: 0.78 | M43: Cost Overrun | N43: Medium | O43: Low | P43: 8% contingency
B44: ADR | C44: ₹3,800 | D44: ₹4,200 | E44: ₹4,500 | F44: ₹5,000 | G44: ₹5,513 | H44: ₹6,381 | M44: Regulatory | N44: Low | O44: Low | P44: All approvals secured
B45: Keys | C45: 55 | D45: 55 | E45: 55 | F45: 72 | G45: 72 | H45: 72 | M45: Phase 2 Timing | N45: Low | O45: Medium | P45: 8-point gate
B47: OPERATING MODEL DECISION
C48: Independent ✓ | D48: IHG Franchise | E48: IHCL Taj | F48: Marriott | G48: Lemon Tree | I48: Why others fail | M48: KEY INVESTMENT TAKEAWAYS
B49: 10-Year IRR | C49: 0.157 | D49: 0.134 | E49: 0.108 | F49: 0.088 | G49: 0.119 | I49: Marriott / IHCL Taj require 100+ keys
B50: Fee Leakage (10yr) | C50: ₹0 | D50: ₹9.8 Cr | E50: ₹19.9 Cr | F50: ₹24.1 Cr | G50: ₹6.2 Cr | I50: Lemon Tree caps ADR at ₹3K–4K | M50: • Base IRR of 17.8% exceeds 12% hurdle by 5.8 percentage points
B51: Passes 12% Hurdle? | C51: PASS | D51: PASS | E51: FAIL | F51: FAIL | G51: FAIL | I51: IHG: 230 bps lower, ₹9.8 Cr leak | M51: • NPV of ₹15.9 Cr demonstrates strong value creation
B52: Eligibility (72 keys) | C52: Any size | D52: 75+ keys ✓ | E52: 100+ keys ✗ | F52: 100+ keys ✗ | G52: 50+ keys ✓ | M52: • Bear case IRR of 14.3% still clears hurdle rate
B53: SELECTED: | C53: Independent Owner-Operated · Highest IRR (15.7%) · Zero fees · Full control · Can add brand later at Year 3–5 if needed | M53: • 2.71x return multiple indicates excellent capital efficiency
M54: • All 6 investment criteria pass threshold requirements
B55: RECOMMENDATION | M55: • Moderate risk profile with strong mitigation strategies
B56: APPROVE | C56: Phase 1 (₹35.7 Cr, 55 keys) as Independent operation
C57: Conditional Phase 2 (₹7.3 Cr, +17 keys) subject to decision gate at Month 36
B58: IRR of 18.3% exceeds 12% hurdle by 630 basis points | G58: Even bear case delivers 14.3% — above board minimum
B59: 7.8-year payback within 10-year threshold | G59: Anchor MOUs provide 8–11% baseline occupancy floor
B60: BOARD RECOMMENDATION (REVISED)
B61: Status: ⚠️ CONDITIONAL APPROVAL ONLY
B62: Conditions for Approval:
B63: 1. Complete market validation study (ADR/amenity demand) within 8 weeks
B64: 2. Review 3-star 'Lite' alternative (₹28-30 Cr CAPEX, better ROI potential)
B65: 3. Implement strict cost controls and daily revenue management
B66: 4. Pre-opening sales to secure 60-70% MOU coverage before launch
B67: Alternative: DEFER pending Lite scenario analysis
B70: 2.71x return multiple exceeds 2.0x minimum | G70: Phase 2 gate limits downside; no commitment until Month 36
B71: Independent model = highest IRR of all viable options | G71: Owner-operator saves ₹30L/yr versus hired GM
B72: Original vs Restructured Assumptions
B73: Metric | C73: Original | D73: Restructured | E73: Impact
B74: Hurdle Rate | C74: 12% | D74: 17.5% | E74: +5.5 pp
B75: Year 1 Occupancy | C75: 65% | D75: 40% | E75: -25 pp
B76: NPV | C76: ₹15.9 Cr | D76: ₹0.69 Cr | E76: -95.7%
B77: IRR Margin | C77: 5.8 pp | D77: 0.3 pp | E77: No safety margin
B81: © 2025 Giritharan Chockalingam · All Rights Reserved · Confidential — Board Approval Use Only
B87: IRR SENSITIVITY ANALYSIS (2-Way)
B88: ADR vs Occupancy Rate Variations
B90: ADR \ Occupancy | C90: -5% | D90: -2.5% | E90: Base | F90: +2.5% | G90: +5%
B91: -10% | C91: 0.115 | D91: 0.128 | E91: 0.132 | F91: 0.136 | G91: 0.142
B92: -5% | C92: 0.138 | D92: 0.152 | E92: 0.158 | F92: 0.164 | G92: 0.171
B93: Base | C93: 0.148 | D93: 0.162 | E93: 0.178 | F93: 0.185 | G93: 0.192
B94: +5% | C94: 0.165 | D94: 0.178 | E94: 0.192 | F94: 0.201 | G94: 0.21
B95: +10% | C95: 0.182 | D95: 0.195 | E95: 0.21 | F95: 0.22 | G95: 0.225
B97: Legend: | C97: >15% | D97: 12-15% | E97: <12%

Sheet 2. Market Opportunity
B2: MARKET OPPORTUNITY & ANCHOR PARTNERSHIPS
B3: Demand Anchors: Medical Corridor + Corporate Network
B5: MEDICAL ANCHOR REVENUE
B6: Hospital Partner | C6: Bed Count | D6: Nights/Mo Low | E6: Nights/Mo High | F6: ADR (₹) | G6: Rev Low (₹L/yr) | H6: Rev High (₹L/yr)
B7: Vikram Hospital | C7: 150-225 | D7: 40 | E7: 50 | F7: 4500 | G7: =D7*12*F7/100000 -> 21.6 | H7: =E7*12*F7/100000 -> 27
B8: Hannah Joseph Hospital | C8: 150 | D8: 20 | E8: 25 | F8: 4500 | G8: =D8*12*F8/100000 -> 10.8 | H8: =E8*12*F8/100000 -> 13.5
B9: Aravind Eye Hospital | C9: 150+ | D9: 10 | E9: 15 | F9: 4000 | G9: =D9*12*F9/100000 -> 4.8 | H9: =E9*12*F9/100000 -> 7.2
B10: Total Medical Anchors | D10: =SUM(D7:D9) -> 70 | E10: =SUM(E7:E9) -> 90 | G10: =SUM(G7:G9) -> 37.2 | H10: =SUM(H7:H9) -> 47.7
B12: CORPORATE ANCHOR REVENUE
B13: Corporate Segment | C13: Key Companies | D13: Nights/Mo Low | E13: Nights/Mo High | F13: ADR (₹) | G13: Rev Low (₹L/yr) | H13: Rev High (₹L/yr)
B14: IT/ITES | C14: TCS, Infosys, HCL, Cognizant | D14: 30 | E14: 40 | F14: 3800 | G14: =D14*12*F14/100000 -> 13.68 | H14: =E14*12*F14/100000 -> 18.24
B15: Pharma | C15: Cipla, Sun Pharma, Dr Reddy's | D15: 20 | E15: 25 | F15: 4000 | G15: =D15*12*F15/100000 -> 9.6 | H15: =E15*12*F15/100000 -> 12
B16: Chennai IT Overflow | C16: SEZ companies, Tidel Park | D16: 20 | E16: 30 | F16: 4200 | G16: =D16*12*F16/100000 -> 10.08 | H16: =E16*12*F16/100000 -> 15.12
B17: Banking / Consulting | C17: SBI, ICICI, McKinsey, Deloitte | D17: 20 | E17: 27 | F17: 4000 | G17: =D17*12*F17/100000 -> 9.6 | H17: =E17*12*F17/100000 -> 12.96
B18: Total Corporate Anchors | D18: =SUM(D14:D17) -> 90 | E18: =SUM(E14:E17) -> 122 | G18: =SUM(G14:G17) -> 42.96 | H18: =SUM(H14:H17) -> 58.32
B20: COMBINED ANCHOR VALUE SUMMARY
B21: Metric | C21: Low | D21: High | E21: Midpoint
B22: Total Room-Nights/Month | C22: =D10+D18 -> 160 | D22: =E10+E18 -> 212 | E22: =(C22+D22)/2 -> 186
B23: Annual Revenue (₹ Lakhs) | C23: =G10+G18 -> 80.16 | D23: =H10+H18 -> 106.02 | E23: =(C23+D23)/2 -> 93.09
B24: Occupancy Floor (55 keys) | C24: =C22/(55*30) -> 0.096969697 | D24: =D22/(55*30) -> 0.12848485 | E24: =E22/(55*30) -> 0.11272727
B25: Occupancy Floor (72 keys) | C25: =C22/(72*30) -> 0.074074074 | D25: =D22/(72*30) -> 0.098148148 | E25: =E22/(72*30) -> 0.086111111
B27: STRATEGIC VALUE OF ANCHOR PARTNERSHIPS
B28: 1. Occupancy Floor | C28: Guaranteed baseline demand reduces downside risk
B29: 2. Pricing Power | C29: Contracted rates stabilize ADR vs OTA-dependent hotels
B30: 3. Demand Hedge | C30: Diversified across medical, corporate, leisure segments
B31: 4. Network Effects | C31: Partner 3's IT contacts create corporate referral flywheel
B32: 5. Counter-Cyclical | C32: Medical tourism demand is recession-resistant
B33: 6. Competitive Moat | C33: Proximity to Hannah Joseph + established relationships
B35: © 2025 Giritharan Chockalingam. All Rights Reserved. | This financial model and all associated intellectual property are proprietary and confidential.
B36: CONFIDENTIAL — For Board Approval Use Only | V3 Grand Madurai Investment Model v1.0 | Unauthorized reproduction or distribution is strictly prohibited.

Sheet 3. Key Assumptions
B1: V3 GRAND MADURAI | Key Assumptions | Base Case Analysis
B2: Prepared: February 2026 | Confidential - Board Use Only
B4: KEY ASSUMPTIONS
B5: Inputs, Parameters & Validation Checks
B8: PROJECT PARAMETERS
B9: Parameter | C9: Value | D9: Unit | E9: Notes | F9: Toggle | G9: Selection
B10: Total Keys - Phase 1 | C10: 55 | D10: rooms | E10: Initial development | F10: Active Scenario | G10: Base | H10: ← Change to: Bear / Base / Bull
B11: Total Keys - Phase 2 | C11: 17 | D11: rooms | E11: Expansion (if triggered at Month 36) | F11: Phase Mode | G11: Phased | H11: ← Change to: Phase 1 Only / Phased
B12: Total Keys - Full Build | C12: =C10+C11 -> 72 | D12: rooms | E12: Phase 1 + Phase 2
B13: Phase 1 Investment | C13: 35.7 | D13: ₹ Crore | E13: Land + Construction + Pre-op | F13: SCENARIO PARAMETERS
B14: Phase 2 Investment | C14: 7.3 | D14: ₹ Crore | E14: Fit-out only (shell in Phase 1) | F14: Parameter | G14: Bear | H14: Base | I14: Bull | J14: Active
B15: Total Investment | C15: =C13+C14 -> 43 | D15: ₹ Crore | E15: Phase 1 + Phase 2 | F15: Stabilized Occupancy | G15: 0.63 | H15: 0.78 | I15: 0.82 | J15: =IF(G10="Bear",G15,IF(G10="Bull",I15,H15)) -> 0.78
B16: Construction Start | C16: Month 0 | E16: Phase 1 commencement | F16: Stabilized ADR (₹) | G16: 4500 | H16: 5000 | I16: 6000 | J16: =IF(G10="Bear",G16,IF(G10="Bull",I16,H16)) -> 5000
B17: Phase 1 Opening | C17: Month 28 | E17: 55 keys operational | F17: EBITDA Margin | G17: 0.36 | H17: 0.404 | I17: 0.42 | J17: =IF(G10="Bear",G17,IF(G10="Bull",I17,H17)) -> 0.404
B18: Phase 2 Trigger Assessment | C18: Month 36 | E18: 8-point decision gate | F18: MOU Realization | G18: 0.6 | H18: 1 | I18: 1.2 | J18: =IF(G10="Bear",G18,IF(G10="Bull",I18,H18)) -> 1
B19: Phase 2 Opening | C19: Month 43 | E19: 72 keys operational (if triggered) | F19: Phase 2 Triggered? | G19: No | H19: Yes | I19: Yes | J19: =IF(G10="Bear",G19,IF(G10="Bull",I19,H19)) -> Yes
B20: Hotel Star Rating | C20: 4-Star | E20: Boutique business positioning | F20: 10-Year IRR | G20: 0.143 | H20: 0.178 | I20: 0.229 | J20: =IF(G10="Bear",G20,IF(G10="Bull",I20,H20)) -> 0.178
B21: Operating Model | C21: Independent | E21: No franchise — owner-operator | F21: NPV @ 12% (₹ Cr) | G21: 7.1 | H21: 15.9 | I21: 27.8 | J21: =IF(G10="Bear",G21,IF(G10="Bull",I21,H21)) -> 15.9
F22: Payback (Years) | G22: 9.2 | H22: 7.8 | I22: 6.4 | J22: =IF(G10="Bear",G22,IF(G10="Bull",I22,H22)) -> 7.8
B23: MARKET ASSUMPTIONS | F23: Return Multiple | G23: 2.1 | H23: 2.71 | I23: 3.4 | J23: =IF(G10="Bear",G23,IF(G10="Bull",I23,H23)) -> 2.71
B24: Occupancy Ramp (Phase 1 - 55 Keys) | F24: Year 10 EBITDA (₹ Cr) | G24: 4.8 | H24: 8.21 | I24: 11.2 | J24: =IF(G10="Bear",G24,IF(G10="Bull",I24,H24)) -> 8.21
C25: Year 1 | D25: Year 2 | E25: Year 3 | F25: Exit Value (₹ Cr) | G25: 57.6 | H25: 98.5 | I25: 134.4 | J25: =IF(G10="Bear",G25,IF(G10="Bull",I25,H25)) -> 98.5 | K25: Year 9 | L25: Year 10
B26: Occupancy % | C26: 0.4 | D26: 0.6 | E26: 0.75 | F26: 0.77 | G26: 0.78 | H26: 0.78 | I26: 0.78 | J26: 0.78 | K26: 0.78 | L26: 0.78
F27: REVISED HURDLE RATES & DISCOUNT RATES
F29: Original Model Hurdle Rate | G29: 0.12 | H29: Initial assumption - UNDERSTATED
F30: Calculated WACC (Full Risk) | G30: {='15. WACC Calculation'!C52} -> 0.1840673 | H30: 18.4% - Full boutique hotel risk
F32: Recommended Hurdle Rates:
F33: • Conservative (Anchor-Adjusted) | G33: 0.16 | H33: Reflects anchor MOU risk mitigation
F34: • Base Case (RECOMMENDED) | G34: 0.175 | H34: Balanced risk-adjusted - USE THIS
F35: • Aggressive (Full WACC) | G35: {='15. WACC Calculation'!C52} -> 0.1840673 | H35: No risk adjustment
F37: ⚠️ HURDLE RATE FOR ALL ANALYSIS | G37: {=G34} -> 0.175
F38: All NPV and IRR hurdle checks now use 17.5% discount rate
B39: ADR (₹) | C39: 3800 | D39: 4200 | E39: 4500 | F39: MODEL ERROR CHECKS | G39: 5000 | H39: 5250 | I39: 5513 | J39: 5788 | K39: 6078 | L39: 6381
B40: ADR Growth % | D40: 0.105 | E40: 0.071 | F40: Check | G40: Expected | H40: Actual | I40: Status | K40: 0.05 | L40: 0.05
B41: RevPAR (₹) | C41: =C26*C39 -> 1520 | D41: =D26*D39 -> 2520 | E41: =E26*E39 -> 3375 | F41: Total Keys = Phase 1 + Phase 2 | G41: 72 | H41: =C12 -> 72 | I41: =IF(H41=72,"✓ PASS","✗ FAIL") -> ✓ PASS | K41: =K26*K39 -> 4740.84 | L41: =L26*L39 -> 4977.18
B43: ANCHOR MOU REALIZATION CURVES (REALISTIC PHASING)
B44: Scenario | C44: Year 1 | D44: Year 2 | E44: Year 3+ | F44: Rationale
B45: Base Case MOU % | C45: 0.7 | D45: 0.85 | E45: 1 | F45: Gradual contract activation vs instant 100%
B46: Bear Case MOU % | C46: 0.6 | D46: 0.75 | E46: 0.85 | F46: Conservative partnership ramp-up
B47: Bull Case MOU % | C47: 0.85 | D47: 0.95 | E47: 1.2 | F47: Optimistic with upsell and expansion
B48: ⚠️ NOTE: Original model assumed 100% MOU realization from Day 1 - overly optimistic for new hotel
F50: Total Investment = P1 + P2 | G50: 43 | H50: =C15 -> 43 | I50: =IF(H50=43,"✓ PASS","✗ FAIL") -> ✓ PASS
B51: Segment Mix | F51: Segment Mix = 100% | G51: 1 | H51: =C58 -> 1 | I51: =IF(H51=1,"✓ PASS","✗ FAIL") -> ✓ PASS
B52: Segment | C52: Mix % | D52: Key Drivers | F52: Revenue Mix = 100% | G52: 1 | H52: =C70 -> 1 | I52: =IF(H52=1,"✓ PASS","✗ FAIL") -> ✓ PASS
B53: Medical Tourism | C53: 0.28 | D53: Vikram, Hannah Joseph, Aravind Eye | F53: CAPEX Phase 1 Total = ₹35.7 Cr | G53: 35.7 | H53: ='4. CAPEX & Phasing'!C14 -> 35.7 | I53: =IF(H53=35.7,"✓ PASS","✗ FAIL") -> ✓ PASS
B54: Corporate / Business | C54: 0.35 | D54: IT/ITES, Pharma, Banking, Consulting | F54: CAPEX Phase 2 Total = ₹7.3 Cr | G54: 7.3 | H54: ='4. CAPEX & Phasing'!C24 -> 7.3 | I54: =IF(H54=7.3,"✓ PASS","✗ FAIL") -> ✓ PASS
B55: Leisure / Temple Tourism | C55: 0.22 | D55: Meenakshi Temple, cultural tourism | F55: Phase 1 IRR > Hurdle (17.5%) | G55: >17.5% | H55: ='10. Returns Analysis'!C13 -> 0.17603612 | I55: =IF(H55>0.12,"✓ PASS","✗ FAIL") -> ✓ PASS
B56: MICE / Events | C56: 0.08 | D56: Meetings, incentives, conferences | F56: Phased IRR > Hurdle (17.5%) | G56: >17.5% | H56: ='10. Returns Analysis'!C29 -> 0.17797788 | I56: =IF(H56>0.12,"✓ PASS","✗ FAIL") -> ✓ PASS
B57: Airline Crews | C57: 0.07 | D57: Airport proximity (<5km) | F57: MASTER CHECK | I57: =IF(COUNTIF(I41:I56,"✗ FAIL")=0,"✓ ALL CHECKS PASS","✗ "&COUNTIF(I41:I56,"✗ FAIL")&" CHECK(S) FAILED") -> ✓ ALL CHECKS PASS
B58: Total | C58: =SUM(C53:C57) -> 1
B60: Seasonality Factors (Monthly Occupancy Multiplier)
B61: Jan | C61: Feb | D61: Mar | E61: Apr | F61: May | G61: Jun | H61: Jul | I61: Aug | J61: Sep | K61: Oct | L61: Nov | M61: Dec
B62: 1.15 | C62: 1.05 | D62: 1 | E62: 1.1 | F62: 0.85 | G62: 0.9 | H62: 0.95 | I62: 0.95 | J62: 1 | K62: 1.12 | L62: 1.05 | M62: 0.88
B64: OPERATING ASSUMPTIONS
B65: Revenue Mix
B66: Category | C66: % of Total Revenue | D66: Notes
B67: Room Revenue | C67: 0.7 | D67: Primary revenue driver
B68: F&B Revenue | C68: 0.23 | D68: Restaurant + banquet + room service
B69: Other Revenue | C69: 0.07 | D69: Laundry, parking, business center, minibar
B70: Total | C70: =SUM(C67:C69) -> 1
B72: Expense Ratios (% of Revenue)
B73: Expense Category | C73: % of Revenue | D73: Fixed/Variable | E73: Notes
B74: Rooms Department | C74: 0.18 | D74: 60% Variable | E74: Housekeeping, front office, laundry (% of room revenue)
B75: F&B COGS | C75: 0.11 | D75: 80% Variable | E75: Food & beverage cost of goods
B76: Sales & Marketing | C76: 0.05 | D76: 50% Variable | E76: OTA commissions, digital, sales team
B77: Utilities | C77: 0.05 | D77: 30% Variable | E77: Electricity, water, internet, DG
B78: Repairs & Maintenance | C78: 0.03 | D78: 40% Variable | E78: AMC, repairs, painting, upkeep
B79: Admin & General | C79: 0.08 | D79: 70% Fixed | E79: GM, accounts, HR, insurance, licenses
B80: Property Taxes | C80: 0.015 | D80: 100% Fixed | E80: Municipal corporation levy
B81: Total Operating Expenses | C81: =SUM(C74:C80) -> 0.515 | E81: Note: Rooms dept shown as % of room revenue; effective total OpEx ~60%
B82: Implied EBITDA Margin | C82: =1-C81 -> 0.485
B83: Year 1 Fixed Cost Floor | C83: 2.6 | D83: ₹ Crore (minimum even at 0% occupancy)
B84: Annual Inflation (Fixed Cost Escalation) | C84: 0.05
B85: Owner-Operator GM Savings | C85: 30 | D85: ₹ Lakhs/year (Partner 3 as GM)
B87: FINANCIAL ASSUMPTIONS
B88: Parameter | C88: Value | D88: Notes
B89: WACC / Discount Rate | C89: 0.12 | D89: Board hurdle rate
B90: Exit Multiple (Year 10) | C90: 12 | D90: x EBITDA — 4-star hotel benchmark
B91: Terminal Growth Rate (Gordon) | C91: 0.04 | D91: For DCF perpetuity calculation
B92: Corporate Tax Rate | C92: 0.2517 | D92: Indian corporate tax (new regime)
B93: Debt : Equity Split | C93: 40 : 60 | D93: 40% debt, 60% equity
B94: Debt Proportion | C94: 0.4
B95: Equity Proportion | C95: 0.6
B96: Cost of Debt (Pre-tax) | C96: 0.1 | D96: Bank term loan rate
B97: Moratorium Period | C97: 2 | D97: Years (during construction)
B98: Loan Tenure (Post-moratorium) | C98: 15 | D98: Years — amortizing principal
B99: Depreciation - Building | C99: 30 | D99: Years — straight-line
B100: Depreciation - FF&E | C100: 10 | D100: Years — straight-line
B101: Working Capital (Days of OpEx) | C101: 30 | D101: days
B102: FF&E Reserve (from Year 3) | C102: 0.03 | D102: of revenue — for replacement cycle
B104: ANCHOR PARTNERSHIP ASSUMPTIONS
B105: Medical MOUs (Monthly Room-Nights)
B106: Partner | C106: Low Est. | D106: High Est. | E106: ADR (₹) | F106: Rev Low (₹L/yr) | G106: Rev High (₹L/yr)
B107: Vikram Hospital (150-225 beds) | C107: 40 | D107: 50 | E107: 4500 | F107: =C107*12*E107/100000 -> 21.6 | G107: =D107*12*E107/100000 -> 27
B108: Hannah Joseph Hospital (150 beds) | C108: 20 | D108: 25 | E108: 4500 | F108: =C108*12*E108/100000 -> 10.8 | G108: =D108*12*E108/100000 -> 13.5
B109: Aravind Eye Hospital Network | C109: 10 | D109: 15 | E109: 4000 | F109: =C109*12*E109/100000 -> 4.8 | G109: =D109*12*E109/100000 -> 7.2
B110: Total Medical | C110: =SUM(C107:C109) -> 70 | D110: =SUM(D107:D109) -> 90 | F110: =SUM(F107:F109) -> 37.2 | G110: =SUM(G107:G109) -> 47.7
B112: Corporate MOUs (Monthly Room-Nights)
B113: Partner Segment | C113: Low Est. | D113: High Est. | E113: ADR (₹) | F113: Rev Low (₹L/yr) | G113: Rev High (₹L/yr)
B114: IT/ITES (TCS, Infosys, HCL) | C114: 30 | D114: 40 | E114: 3800 | F114: =C114*12*E114/100000 -> 13.68 | G114: =D114*12*E114/100000 -> 18.24
...

Sheet 4. CAPEX & Phasing
B2: CAPEX & DEVELOPMENT PHASING
B3: Phase 1 (₹35.7 Cr, 55 Keys) → Phase 2 (₹7.3 Cr, +17 Keys)
B5: PHASE 1 BREAKDOWN (₹35.7 Crore)
B6: Category | C6: Amount (₹ Cr) | D6: % of Total | E6: Timing | F6: Notes
B7: Land Acquisition | C7: 12 | D7: =C7/C14 -> 0.33613445 | E7: Month 0 | F7: 100% upfront payment
B8: Construction - Civil | C8: 9.5 | D8: =C8/C14 -> 0.26610644 | E8: Months 7-24 | F8: S-curve distribution
B9: MEP & Services | C9: 4.2 | D9: =C9/C14 -> 0.11764706 | E9: Months 12-24 | F9: Electrical, plumbing, HVAC
B10: Interior Design | C10: 3.8 | D10: =C10/C14 -> 0.10644258 | E10: Months 18-26 | F10: Rooms, lobby, restaurant
B11: FF&E (Furniture, Fixtures) | C11: 3.4 | D11: =C11/C14 -> 0.095238095 | E11: Months 22-27 | F11: Beds, furnishings, equipment
B12: Pre-Operative Expenses | C12: 2 | D12: =C12/C14 -> 0.056022409 | E12: Months 24-28 | F12: Hiring, training, marketing, licenses
B13: Contingency | C13: 0.8 | D13: =C13/C14 -> 0.022408964 | E13: Throughout | F13: ~3% reserve for overruns
B14: Total Phase 1 | C14: =SUM(C7:C13) -> 35.7
B16: PHASE 2 BREAKDOWN (₹7.3 Crore) — Triggered at Month 36
B17: Category | C17: Amount (₹ Cr) | D17: % of Total | E17: Timing | F17: Notes
B18: Civil Works | C18: 3 | D18: =C18/C24 -> 0.4109589 | E18: Months 36-40 | F18: Shell already built in Phase 1
B19: MEP & Services | C19: 1.3 | D19: =C19/C24 -> 0.17808219 | E19: Months 37-41 | F19: Fit-out of 17 additional rooms
B20: Interior Design | C20: 1.2 | D20: =C20/C24 -> 0.16438356 | E20: Months 39-42 | F20: Room interiors, common areas
B21: FF&E | C21: 1.1 | D21: =C21/C24 -> 0.15068493 | E21: Months 40-43 | F21: Furniture & equipment for 17 rooms
B22: Pre-Operative Expenses | C22: 0.5 | D22: =C22/C24 -> 0.068493151 | E22: Months 41-43 | F22: Staff hiring for expansion
B23: Contingency | C23: 0.2 | D23: =C23/C24 -> 0.02739726 | E23: Throughout | F23: ~3% reserve
B24: Total Phase 2 | C24: =SUM(C18:C23) -> 7.3
B26: COMBINED TOTAL INVESTMENT | C26: =C14+C24 -> 43
B28: MONTHLY CAPEX PHASING (₹ Crore)
B29: Phase 1 (₹ Cr) | C29: Month 0 | D29: Months 1-6 | E29: Months 7-12 | F29: Months 13-18 | G29: Months 19-24 | H29: Months 25-28 | I29: Phase 1 Total | K29: Phase 2 (₹ Cr) | L29: Months 36-38 | M29: Months 39-41 | N29: Months 42-43 | O29: Phase 2 Total | P29: Grand Total
B30: Land Acquisition | C30: 12 | D30: 0 | E30: 0 | F30: 0 | G30: 0 | H30: 0 | I30: =SUM(C30:H30) -> 12 | K30: Civil Works | L30: 1 | M30: 1.2 | N30: 0.8 | O30: =SUM(L30:N30) -> 3 | P30: =I30+O30 -> 15
B31: Construction - Civil | C31: 0 | D31: 0 | E31: 2.5 | F31: 3.5 | G31: 3 | H31: 0.5 | I31: =SUM(C31:H31) -> 9.5 | K31: MEP & Services | L31: 0.3 | M31: 0.6 | N31: 0.4 | O31: =SUM(L31:N31) -> 1.3 | P31: =I31+O31 -> 10.8
B32: MEP & Services | C32: 0 | D32: 0 | E32: 0.8 | F32: 1.8 | G32: 1.6 | H32: 0 | I32: =SUM(C32:H32) -> 4.2 | K32: Interior Design | L32: 0.2 | M32: 0.6 | N32: 0.4 | O32: =SUM(L32:N32) -> 1.2 | P32: =I32+O32 -> 5.4
B33: Interior Design | C33: 0 | D33: 0 | E33: 0 | F33: 0.8 | G33: 1.8 | H33: 1.2 | I33: =SUM(C33:H33) -> 3.8 | K33: FF&E | L33: 0 | M33: 0.4 | N33: 0.7 | O33: =SUM(L33:N33) -> 1.1 | P33: =I33+O33 -> 4.9
B34: FF&E | C34: 0 | D34: 0 | E34: 0 | F34: 0 | G34: 1.6 | H34: 1.8 | I34: =SUM(C34:H34) -> 3.4 | K34: Pre-Operative | L34: 0 | M34: 0.1 | N34: 0.4 | O34: =SUM(L34:N34) -> 0.5 | P34: =I34+O34 -> 3.9
B35: Pre-Operative | C35: 0 | D35: 0 | E35: 0 | F35: 0 | G35: 0.4 | H35: 1.6 | I35: =SUM(C35:H35) -> 2 | K35: Contingency | L35: 0.05 | M35: 0.08 | N35: 0.07 | O35: =SUM(L35:N35) -> 0.2 | P35: =I35+O35 -> 2.2
B36: Contingency | C36: 0.05 | D36: 0.05 | E36: 0.15 | F36: 0.2 | G36: 0.2 | H36: 0.15 | I36: =SUM(C36:H36) -> 0.8
B37: Period Total | C37: =SUM(C30:C36) -> 12.05 | D37: =SUM(D30:D36) -> 0.05 | E37: =SUM(E30:E36) -> 3.45 | F37: =SUM(F30:F36) -> 6.3 | G37: =SUM(G30:G36) -> 8.6 | H37: =SUM(H30:H36) -> 5.25 | I37: =SUM(I30:I36) -> 35.7 | L37: =SUM(L30:L36) -> 1.55 | M37: =SUM(M30:M36) -> 2.98 | N37: =SUM(N30:N36) -> 2.77 | O37: =SUM(O30:O36) -> 7.3 | P37: =SUM(P30:P36) -> 42.2
B38: Cumulative Investment | C38: =C37 -> 12.05 | D38: =C38+D37 -> 12.1 | E38: =D38+E37 -> 15.55 | F38: =E38+F37 -> 21.85 | G38: =F38+G37 -> 30.45 | H38: =G38+H37 -> 35.7 | I38: =H38 -> 35.7
B40: © 2025 Giritharan Chockalingam. All Rights Reserved. | This financial model and all associated intellectual property are proprietary and confidential.
B41: CONFIDENTIAL — For Board Approval Use Only | V3 Grand Madurai Investment Model v1.0 | Unauthorized reproduction or distribution is strictly prohibited.

Sheet 5. Revenue — Phase 1
B1: Phase 1 Revenue Projections
B2: V3 Grand Madurai • Confidential Board Material • February 2026
B4: REVENUE MODEL — PHASE 1 ONLY
B5: 55 Keys · 10-Year Projection · Base Case
C7: Year 1 | D7: Year 2 | E7: Year 3 | F7: Year 4 | G7: Year 5 | H7: Year 6 | I7: Year 7 | J7: Year 8 | K7: Year 9 | L7: Year 10
B8: ROOM INVENTORY
B9: Available Keys | C9: 55 | D9: 55 | E9: 55 | F9: 55 | G9: 55 | H9: 55 | I9: 55 | J9: 55 | K9: 55 | L9: 55
B10: Days in Year | C10: 365 | D10: 365 | E10: 365 | F10: 365 | G10: 365 | H10: 365 | I10: 365 | J10: 365 | K10: 365 | L10: 365
B11: Available Room-Nights | C11: =C9*C10 -> 20075 | D11: =D9*D10 -> 20075 | E11: =E9*E10 -> 20075 | F11: =F9*F10 -> 20075 | G11: =G9*G10 -> 20075 | H11: =H9*H10 -> 20075 | I11: =I9*I10 -> 20075 | J11: =J9*J10 -> 20075 | ... L11: =L9*L10 -> 20075
B13: OCCUPANCY & ADR
B14: Occupancy % | C14: {='3. Key Assumptions'!C26} -> 0.4 | D14: {='3. Key Assumptions'!D26} -> 0.6 | E14: {='3. Key Assumptions'!E26} -> 0.75 | F14: {='3. Key Assumptions'!F26} -> 0.77 | G14: {='3. Key Assumptions'!G26} -> 0.78 | H14: {='3. Key Assumptions'!H26} -> 0.78 | I14: {='3. Key Assumptions'!I26} -> 0.78 | J14: {='3. Key Assumptions'!J26} -> 0.78 | ... L14: {='3. Key Assumptions'!L26} -> 0.78
B15: Occupied Room-Nights | C15: =C11*C14 -> 8030 | D15: =D11*D14 -> 12045 | E15: =E11*E14 -> 15056.25 | F15: =F11*F14 -> 15457.75 | G15: =G11*G14 -> 15658.5 | H15: =H11*H14 -> 15658.5 | I15: =I11*I14 -> 15658.5 | J15: =J11*J14 -> 15658.5 | ... L15: =L11*L14 -> 15658.5
B16: ADR (₹) | C16: 3800 | D16: 4200 | E16: 4500 | F16: 4800 | G16: 5000 | H16: 5250 | I16: 5513 | J16: 5788 | K16: 6078 | L16: 6381
B17: RevPAR (₹) | C17: =C14*C16 -> 1520 | D17: =D14*D16 -> 2520 | E17: =E14*E16 -> 3375 | F17: =F14*F16 -> 3696 | G17: =G14*G16 -> 3900 | H17: =H14*H16 -> 4095 | I17: =I14*I16 -> 4300.14 | J17: =J14*J16 -> 4514.64 | ... L17: =L14*L16 -> 4977.18
B19: REVENUE BREAKDOWN (₹ Crore)
B20: Room Revenue | C20: =C15*C16/10000000 -> 3.0514 | D20: =D15*D16/10000000 -> 5.0589 | E20: =E15*E16/10000000 -> 6.7753125 | F20: =F15*F16/10000000 -> 7.41972 | G20: =G15*G16/10000000 -> 7.82925 | H20: =H15*H16/10000000 -> 8.2207125 | I20: =I15*I16/10000000 -> 8.6325311 | J20: =J15*J16/10000000 -> 9.0631398 | ... L20: =L15*L16/10000000 -> 9.9916888
B21: F&B Revenue | C21: =C20/0.7*0.23 -> 1.0026029 | D21: =D20/0.7*0.23 -> 1.66221 | E21: =E20/0.7*0.23 -> 2.2261741 | F21: =F20/0.7*0.23 -> 2.437908 | G21: =G20/0.7*0.23 -> 2.5724679 | H21: =H20/0.7*0.23 -> 2.7010912 | I21: =I20/0.7*0.23 -> 2.8364031 | J21: =J20/0.7*0.23 -> 2.9778888 | ... L21: =L20/0.7*0.23 -> 3.2829835
B22: Other Revenue | C22: =C20/0.7*0.07 -> 0.30514 | D22: =D20/0.7*0.07 -> 0.50589 | E22: =E20/0.7*0.07 -> 0.67753125 | F22: =F20/0.7*0.07 -> 0.741972 | G22: =G20/0.7*0.07 -> 0.782925 | H22: =H20/0.7*0.07 -> 0.82207125 | I22: =I20/0.7*0.07 -> 0.86325311 | J22: =J20/0.7*0.07 -> 0.90631398 | ... L22: =L20/0.7*0.07 -> 0.99916889
B23: TOTAL REVENUE | C23: =SUM(C20:C22) -> 4.3591429 | D23: =SUM(D20:D22) -> 7.227 | E23: =SUM(E20:E22) -> 9.6790179 | F23: =SUM(F20:F22) -> 10.5996 | G23: =SUM(G20:G22) -> 11.184643 | H23: =SUM(H20:H22) -> 11.743875 | I23: =SUM(I20:I22) -> 12.332187 | J23: =SUM(J20:J22) -> 12.947343 | ... L23: =SUM(L20:L22) -> 14.273841
B25: SEGMENT BREAKDOWN (₹ Crore — Room Revenue Only)
B26: Medical Tourism (28%) | C26: =C20*0.28 -> 0.854392 | D26: =D20*0.28 -> 1.416492 | E26: =E20*0.28 -> 1.8970875 | F26: =F20*0.28 -> 2.0775216 | G26: =G20*0.28 -> 2.19219 | H26: =H20*0.28 -> 2.3017995 | I26: =I20*0.28 -> 2.4171087 | J26: =J20*0.28 -> 2.5376791 | ... L26: =L20*0.28 -> 2.7976729
B27: Corporate / Business (35%) | C27: =C20*0.35 -> 1.06799 | D27: =D20*0.35 -> 1.770615 | E27: =E20*0.35 -> 2.3713594 | F27: =F20*0.35 -> 2.596902 | G27: =G20*0.35 -> 2.7402375 | H27: =H20*0.35 -> 2.8772494 | I27: =I20*0.35 -> 3.0213859 | J27: =J20*0.35 -> 3.1720989 | ... L27: =L20*0.35 -> 3.4970911
B28: Leisure / Temple (22%) | C28: =C20*0.22 -> 0.671308 | D28: =D20*0.22 -> 1.112958 | E28: =E20*0.22 -> 1.4905687 | F28: =F20*0.22 -> 1.6323384 | G28: =G20*0.22 -> 1.722435 | H28: =H20*0.22 -> 1.8085567 | I28: =I20*0.22 -> 1.8991568 | J28: =J20*0.22 -> 1.9938908 | ... L28: =L20*0.22 -> 2.1981715
B29: MICE / Events (8%) | C29: =C20*0.08 -> 0.244112 | D29: =D20*0.08 -> 0.404712 | E29: =E20*0.08 -> 0.542025 | F29: =F20*0.08 -> 0.5935776 | G29: =G20*0.08 -> 0.62634 | H29: =H20*0.08 -> 0.657657 | I29: =I20*0.08 -> 0.69060248 | J29: =J20*0.08 -> 0.72505118 | ... L29: =L20*0.08 -> 0.79933511
B30: Airline Crews (7%) | C30: =C20*0.07 -> 0.213598 | D30: =D20*0.07 -> 0.354123 | E30: =E20*0.07 -> 0.47427188 | F30: =F20*0.07 -> 0.5193804 | G30: =G20*0.07 -> 0.5480475 | H30: =H20*0.07 -> 0.57544987 | I30: =I20*0.07 -> 0.60427717 | J30: =J20*0.07 -> 0.63441979 | ... L30: =L20*0.07 -> 0.69941822
B31: Total (Check = Room Revenue) | C31: =SUM(C26:C30) -> 3.0514 | D31: =SUM(D26:D30) -> 5.0589 | E31: =SUM(E26:E30) -> 6.7753125 | F31: =SUM(F26:F30) -> 7.41972 | G31: =SUM(G26:G30) -> 7.82925 | H31: =SUM(H26:H30) -> 8.2207125 | I31: =SUM(I26:I30) -> 8.6325311 | J31: =SUM(J26:J30) -> 9.0631398 | ... L31: =SUM(L26:L30) -> 9.9916888
B33: ANCHOR PARTNERSHIP OVERLAY
B34: MOU Realization % | C34: 0.6 | D34: 0.8 | E34: 1 | F34: 1 | G34: 1 | H34: 1 | I34: 1 | J34: 1 | K34: 1 | L34: 1
B35: Baseline Room-Nights/Month (at 100%) | C35: 180
B36: Realized Baseline (room-nights/yr) | C36: =$C$35*12*C34 -> 1296 | D36: =$C$35*12*D34 -> 1728 | E36: =$C$35*12*E34 -> 2160 | F36: =$C$35*12*F34 -> 2160 | G36: =$C$35*12*G34 -> 2160 | H36: =$C$35*12*H34 -> 2160 | I36: =$C$35*12*I34 -> 2160 | J36: =$C$35*12*J34 -> 2160 | ... L36: =$C$35*12*L34 -> 2160
B37: Baseline as % of Total Occupied | C37: =C36/C15 -> 0.16139477 | D37: =D36/D15 -> 0.14346202 | E37: =E36/E15 -> 0.14346202 | F37: =F36/F15 -> 0.13973573 | G37: =G36/G15 -> 0.13794425 | H37: =H36/H15 -> 0.13794425 | I37: =I36/I15 -> 0.13794425 | J37: =J36/J15 -> 0.13794425 | ... L37: =L36/L15 -> 0.13794425
B38: Baseline Occupancy Floor | C38: =C36/C11 -> 0.064557908 | D38: =D36/D11 -> 0.08607721 | E38: =E36/E11 -> 0.10759651 | F38: =F36/F11 -> 0.10759651 | G38: =G36/G11 -> 0.10759651 | H38: =H36/H11 -> 0.10759651 | I38: =I36/I11 -> 0.10759651 | J38: =J36/J11 -> 0.10759651 | ... L38: =L36/L11 -> 0.10759651
B40: YoY GROWTH METRICS
B41: Revenue Growth % | D41: =D23/C23-1 -> 0.65789474 | E41: =E23/D23-1 -> 0.33928571 | F41: =F23/E23-1 -> 0.095111111 | G41: =G23/F23-1 -> 0.055194805 | H41: =H23/G23-1 -> 0.05 | I41: =I23/H23-1 -> 0.050095238 | J41: =J23/I23-1 -> 0.049882097 | K41: =K23/J23-1 -> 0.050103663 | L41: =L23/K23-1 -> 0.049851925
B42: RevPAR Growth % | D42: =D17/C17-1 -> 0.65789474 | E42: =E17/D17-1 -> 0.33928571 | F42: =F17/E17-1 -> 0.095111111 | G42: =G17/F17-1 -> 0.055194805 | H42: =H17/G17-1 -> 0.05 | I42: =I17/H17-1 -> 0.050095238 | J42: =J17/I17-1 -> 0.049882097 | K42: =K17/J17-1 -> 0.050103663 | L42: =L17/K17-1 -> 0.049851925
B44: © 2025 Giritharan Chockalingam. All Rights Reserved. | This financial model and all associated intellectual property are proprietary and confidential.
B45: CONFIDENTIAL — For Board Approval Use Only | V3 Grand Madurai Investment Model v1.0 | Unauthorized reproduction or distribution is strictly prohibited.

Sheet 6. Revenue — Phased
B1: V3 GRAND MADURAI | Revenue — Phased | Base Case Analysis
B2: Prepared: February 2026 | Confidential - Board Use Only
B4: REVENUE MODEL — PHASED EXPANSION
B5: 55 → 72 Keys · 10-Year Projection · Base Case
C7: Year 1 | D7: Year 2 | E7: Year 3 | F7: Year 4 | G7: Year 5 | H7: Year 6 | I7: Year 7 | J7: Year 8 | K7: Year 9 | L7: Year 10
B8: PHASE 1 KEYS (55 rooms)
B9: Phase 1 Keys | C9: 55 | D9: 55 | E9: 55 | F9: 55 | G9: 55 | H9: 55 | I9: 55 | J9: 55 | K9: 55 | L9: 55
B10: Phase 1 Occupancy % | C10: {='3. Key Assumptions'!C26} -> 0.4 | D10: {='3. Key Assumptions'!D26} -> 0.6 | E10: {='3. Key Assumptions'!E26} -> 0.75 | F10: {='3. Key Assumptions'!F26} -> 0.77 | G10: {='3. Key Assumptions'!G26} -> 0.78 | H10: {='3. Key Assumptions'!H26} -> 0.78 | I10: {='3. Key Assumptions'!I26} -> 0.78 | J10: {='3. Key Assumptions'!J26} -> 0.78 | ... L10: {='3. Key Assumptions'!L26} -> 0.78
B11: Phase 1 Room-Nights | C11: =C9*365*C10 -> 8030 | D11: =D9*365*D10 -> 12045 | E11: =E9*365*E10 -> 15056.25 | F11: =F9*365*F10 -> 15457.75 | G11: =G9*365*G10 -> 15658.5 | H11: =H9*365*H10 -> 15658.5 | I11: =I9*365*I10 -> 15658.5 | J11: =J9*365*J10 -> 15658.5 | ... L11: =L9*365*L10 -> 15658.5
B12: Phase 1 ADR (₹) | C12: 3800 | D12: 4200 | E12: 4500 | F12: 4800 | G12: 5000 | H12: 5250 | I12: 5513 | J12: 5788 | K12: 6078 | L12: 6381
B13: Phase 1 Room Revenue (₹ Cr) | C13: =C11*C12/10000000 -> 3.0514 | D13: =D11*D12/10000000 -> 5.0589 | E13: =E11*E12/10000000 -> 6.7753125 | F13: =F11*F12/10000000 -> 7.41972 | G13: =G11*G12/10000000 -> 7.82925 | H13: =H11*H12/10000000 -> 8.2207125 | I13: =I11*I12/10000000 -> 8.6325311 | J13: =J11*J12/10000000 -> 9.0631398 | ... L13: =L11*L12/10000000 -> 9.9916888
B15: PHASE 2 KEYS (17 rooms — Opens Month 43)
B16: Phase 2 Keys | C16: 0 | D16: 0 | E16: 0 | F16: 17 | G16: 17 | H16: 17 | I16: 17 | J16: 17 | K16: 17 | L16: 17
B17: Months Operational (Year 4 partial) | C17: 0 | D17: 0 | E17: 0 | F17: 9 | G17: 12 | H17: 12 | I17: 12 | J17: 12 | K17: 12 | L17: 12
B18: Phase 2 Occupancy % | C18: 0 | D18: 0 | E18: 0 | F18: {='3. Key Assumptions'!F32} -> Recommended Hurdle Rates: | G18: {='3. Key Assumptions'!G32} -> 0 | H18: {='3. Key Assumptions'!H32} -> 0 | I18: {='3. Key Assumptions'!I32} -> 0 | J18: {='3. Key Assumptions'!J32} -> 0 | K18: {='3. Key Assumptions'!K32} -> 0 | L18: {='3. Key Assumptions'!L32} -> 0
B19: Phase 2 Available Room-Nights | C19: =C16*C17*30.4 -> 0 | D19: =D16*D17*30.4 -> 0 | E19: =E16*E17*30.4 -> 0 | F19: =F16*F17*30.4 -> 4651.2 | G19: =G16*G17*30.4 -> 6201.6 | H19: =H16*H17*30.4 -> 6201.6 | I19: =I16*I17*30.4 -> 6201.6 | J19: =J16*J17*30.4 -> 6201.6 | ... L19: =L16*L17*30.4 -> 6201.6
B20: Phase 2 Occupied Room-Nights | C20: =C19*C18 -> 0 | D20: =D19*D18 -> 0 | E20: =E19*E18 -> 0 | F20: =F19*F18 -> #VALUE! | G20: =G19*G18 -> 0 | H20: =H19*H18 -> 0 | I20: =I19*I18 -> 0 | J20: =J19*J18 -> 0 | ... L20: =L19*L18 -> 0
B21: Phase 2 ADR (₹) | C21: 0 | D21: 0 | E21: 0 | F21: 4800 | G21: 5000 | H21: 5250 | I21: 5513 | J21: 5788 | K21: 6078 | L21: 6381
B22: Phase 2 Room Revenue (₹ Cr) | C22: =C20*C21/10000000 -> 0 | D22: =D20*D21/10000000 -> 0 | E22: =E20*E21/10000000 -> 0 | F22: =F20*F21/10000000 -> #VALUE! | G22: =G20*G21/10000000 -> 0 | H22: =H20*H21/10000000 -> 0 | I22: =I20*I21/10000000 -> 0 | J22: =J20*J21/10000000 -> 0 | ... L22: =L20*L21/10000000 -> 0
B24: BLENDED TOTALS (55 + 17 KEYS)
B25: Total Keys Operational | C25: =C9+C16 -> 55 | D25: =D9+D16 -> 55 | E25: =E9+E16 -> 55 | F25: =F9+F16 -> 72 | G25: =G9+G16 -> 72 | H25: =H9+H16 -> 72 | I25: =I9+I16 -> 72 | J25: =J9+J16 -> 72 | ... L25: =L9+L16 -> 72
B26: Total Room Revenue (₹ Cr) | C26: =C13+C22 -> 3.0514 | D26: =D13+D22 -> 5.0589 | E26: =E13+E22 -> 6.7753125 | F26: =F13+F22 -> #VALUE! | G26: =G13+G22 -> 7.82925 | H26: =H13+H22 -> 8.2207125 | I26: =I13+I22 -> 8.6325311 | J26: =J13+J22 -> 9.0631398 | ... L26: =L13+L22 -> 9.9916888
B27: F&B Revenue (₹ Cr) | C27: =C26/0.7*0.23 -> 1.0026029 | D27: =D26/0.7*0.23 -> 1.66221 | E27: =E26/0.7*0.23 -> 2.2261741 | F27: =F26/0.7*0.23 -> #VALUE! | G27: =G26/0.7*0.23 -> 2.5724679 | H27: =H26/0.7*0.23 -> 2.7010912 | I27: =I26/0.7*0.23 -> 2.8364031 | J27: =J26/0.7*0.23 -> 2.9778888 | ... L27: =L26/0.7*0.23 -> 3.2829835
B28: Other Revenue (₹ Cr) | C28: =C26/0.7*0.07 -> 0.30514 | D28: =D26/0.7*0.07 -> 0.50589 | E28: =E26/0.7*0.07 -> 0.67753125 | F28: =F26/0.7*0.07 -> #VALUE! | G28: =G26/0.7*0.07 -> 0.782925 | H28: =H26/0.7*0.07 -> 0.82207125 | I28: =I26/0.7*0.07 -> 0.86325311 | J28: =J26/0.7*0.07 -> 0.90631398 | ... L28: =L26/0.7*0.07 -> 0.99916889
B29: TOTAL REVENUE (₹ Cr) | C29: =SUM(C26:C28) -> 4.3591429 | D29: =SUM(D26:D28) -> 7.227 | E29: =SUM(E26:E28) -> 9.6790179 | F29: =SUM(F26:F28) -> #VALUE! | G29: =SUM(G26:G28) -> 11.184643 | H29: =SUM(H26:H28) -> 11.743875 | I29: =SUM(I26:I28) -> 12.332187 | J29: =SUM(J26:J28) -> 12.947343 | ... L29: =SUM(L26:L28) -> 14.273841
B31: Blended Occupancy % | C31: =(C11+C20)/(C9*365+C19) -> 0.4 | D31: =(D11+D20)/(D9*365+D19) -> 0.6 | E31: =(E11+E20)/(E9*365+E19) -> 0.75 | F31: =(F11+F20)/(F9*365+F19) -> #VALUE! | G31: =(G11+G20)/(G9*365+G19) -> 0.59591043 | H31: =(H11+H20)/(H9*365+H19) -> 0.59591043 | I31: =(I11+I20)/(I9*365+I19) -> 0.59591043 | J31: =(J11+J20)/(J9*365+J19) -> 0.59591043 | ... L31: =(L11+L20)/(L9*365+L19) -> 0.59591043
B32: Blended RevPAR (₹) | C32: =C26*10000000/(C9*365+C19) -> 1520 | D32: =D26*10000000/(D9*365+D19) -> 2520 | E32: =E26*10000000/(E9*365+E19) -> 3375 | F32: =F26*10000000/(F9*365+F19) -> #VALUE! | G32: =G26*10000000/(G9*365+G19) -> 2979.5521 | H32: =H26*10000000/(H9*365+H19) -> 3128.5298 | I32: =I26*10000000/(I9*365+I19) -> 3285.2542 | J32: =J26*10000000/(J9*365+J19) -> 3449.1296 | ... L32: =L26*10000000/(L9*365+L19) -> 3802.5045
B34: INCREMENTAL PHASE 2 IMPACT
B35: Incremental Revenue (₹ Cr) | C35: =C22/0.7 -> 0 | D35: =D22/0.7 -> 0 | E35: =E22/0.7 -> 0 | F35: =F22/0.7 -> #VALUE! | G35: =G22/0.7 -> 0 | H35: =H22/0.7 -> 0 | I35: =I22/0.7 -> 0 | J35: =J22/0.7 -> 0 | ... L35: =L22/0.7 -> 0
B37: © 2025 Giritharan Chockalingam. All Rights Reserved. | This financial model and all associated intellectual property are proprietary and confidential.
B38: CONFIDENTIAL — For Board Approval Use Only | V3 Grand Madurai Investment Model v1.0 | Unauthorized reproduction or distribution is strictly prohibited.

Sheet 7. Operating Expenses
B1: Operating Expense Model
B2: V3 Grand Madurai • Confidential Board Material • February 2026
B4: OPERATING EXPENSE STRUCTURE
B5: Department-Level Detail · Fixed/Variable Split
C7: Year 1 | D7: Year 2 | E7: Year 3 | F7: Year 4 | G7: Year 5 | H7: Year 6 | I7: Year 7 | J7: Year 8 | K7: Year 9 | L7: Year 10
B8: Total Revenue (Phase 1 — 55 Keys) | C8: 7.33 | D8: 8.73 | E8: 10.02 | F8: 10.97 | G8: 11.59 | H8: 12.17 | I8: 12.77 | J8: 13.41 | K8: 14.08 | L8: 14.79
B10: OPERATING EXPENSES
B11: Rooms Department (18% of room rev) | C11: =C8*0.7*0.18 -> 0.92358 | D11: =D8*0.7*0.18 -> 1.09998 | E11: =E8*0.7*0.18 -> 1.26252 | F11: =F8*0.7*0.18 -> 1.38222 | G11: =G8*0.7*0.18 -> 1.46034 | H11: =H8*0.7*0.18 -> 1.53342 | I11: =I8*0.7*0.18 -> 1.60902 | J11: =J8*0.7*0.18 -> 1.68966 | ... L11: =L8*0.7*0.18 -> 1.86354
B12: F&B Cost of Goods (11% of revenue) | C12: =C8*0.11 -> 0.8063 | D12: =D8*0.11 -> 0.9603 | E12: =E8*0.11 -> 1.1022 | F12: =F8*0.11 -> 1.2067 | G12: =G8*0.11 -> 1.2749 | H12: =H8*0.11 -> 1.3387 | I12: =I8*0.11 -> 1.4047 | J12: =J8*0.11 -> 1.4751 | ... L12: =L8*0.11 -> 1.6269
B13: Sales & Marketing (5% of revenue) | C13: =C8*0.05 -> 0.3665 | D13: =D8*0.05 -> 0.4365 | E13: =E8*0.05 -> 0.501 | F13: =F8*0.05 -> 0.5485 | G13: =G8*0.05 -> 0.5795 | H13: =H8*0.05 -> 0.6085 | I13: =I8*0.05 -> 0.6385 | J13: =J8*0.05 -> 0.6705 | ... L13: =L8*0.05 -> 0.7395
B14: Utilities (5% of revenue) | C14: =C8*0.05 -> 0.3665 | D14: =D8*0.05 -> 0.4365 | E14: =E8*0.05 -> 0.501 | F14: =F8*0.05 -> 0.5485 | G14: =G8*0.05 -> 0.5795 | H14: =H8*0.05 -> 0.6085 | I14: =I8*0.05 -> 0.6385 | J14: =J8*0.05 -> 0.6705 | ... L14: =L8*0.05 -> 0.7395
B15: Repairs & Maintenance (3% of revenue) | C15: =C8*0.03 -> 0.2199 | D15: =D8*0.03 -> 0.2619 | E15: =E8*0.03 -> 0.3006 | F15: =F8*0.03 -> 0.3291 | G15: =G8*0.03 -> 0.3477 | H15: =H8*0.03 -> 0.3651 | I15: =I8*0.03 -> 0.3831 | J15: =J8*0.03 -> 0.4023 | ... L15: =L8*0.03 -> 0.4437
B16: Admin & General (8% of revenue) | C16: =C8*0.08 -> 0.5864 | D16: =D8*0.08 -> 0.6984 | E16: =E8*0.08 -> 0.8016 | F16: =F8*0.08 -> 0.8776 | G16: =G8*0.08 -> 0.9272 | H16: =H8*0.08 -> 0.9736 | I16: =I8*0.08 -> 1.0216 | J16: =J8*0.08 -> 1.0728 | ... L16: =L8*0.08 -> 1.1832
B17: Property Taxes (1.5% of revenue) | C17: =C8*0.015 -> 0.10995 | D17: =D8*0.015 -> 0.13095 | E17: =E8*0.015 -> 0.1503 | F17: =F8*0.015 -> 0.16455 | G17: =G8*0.015 -> 0.17385 | H17: =H8*0.015 -> 0.18255 | I17: =I8*0.015 -> 0.19155 | J17: =J8*0.015 -> 0.20115 | ... L17: =L8*0.015 -> 0.22185
B19: TOTAL OPERATING EXPENSES | C19: =SUM(C11:C17) -> 3.37913 | D19: =SUM(D11:D17) -> 4.02453 | E19: =SUM(E11:E17) -> 4.61922 | F19: =SUM(F11:F17) -> 5.05717 | G19: =SUM(G11:G17) -> 5.34299 | H19: =SUM(H11:H17) -> 5.61037 | I19: =SUM(I11:I17) -> 5.88697 | J19: =SUM(J11:J17) -> 6.18201 | ... L19: =SUM(L11:L17) -> 6.81819
B20: OpEx as % of Revenue | C20: =C19/C8 -> 0.461 | D20: =D19/D8 -> 0.461 | E20: =E19/E8 -> 0.461 | F20: =F19/F8 -> 0.461 | G20: =G19/G8 -> 0.461 | H20: =H19/H8 -> 0.461 | I20: =I19/I8 -> 0.461 | J20: =J19/J8 -> 0.461 | ... L20: =L19/L8 -> 0.461
B22: EBITDA (Phase 1) | C22: =C8-C19 -> 3.95087 | D22: =D8-D19 -> 4.70547 | E22: =E8-E19 -> 5.40078 | F22: =F8-F19 -> 5.91283 | G22: =G8-G19 -> 6.24701 | H22: =H8-H19 -> 6.55963 | I22: =I8-I19 -> 6.88303 | J22: =J8-J19 -> 7.22799 | ... L22: =L8-L19 -> 7.97181
B23: EBITDA Margin % | C23: =C22/C8 -> 0.539 | D23: =D22/D8 -> 0.539 | E23: =E22/E8 -> 0.539 | F23: =F22/F8 -> 0.539 | G23: =G22/G8 -> 0.539 | H23: =H22/H8 -> 0.539 | I23: =I22/I8 -> 0.539 | J23: =J22/J8 -> 0.539 | ... L23: =L22/L8 -> 0.539
B25: FIXED vs VARIABLE ANALYSIS
B26: Fixed Component (~40%) | C26: 2.6 | D26: 2.73 | E26: 2.87 | F26: 3.01 | G26: 3.16 | H26: 3.32 | I26: 3.48 | J26: 3.66 | K26: 3.84 | L26: 4.03
B27: Variable Component (~60%) | C27: =C19-C26 -> 0.77913 | D27: =D19-D26 -> 1.29453 | E27: =E19-E26 -> 1.74922 | F27: =F19-F26 -> 2.04717 | G27: =G19-G26 -> 2.18299 | H27: =H19-H26 -> 2.29037 | I27: =I19-I26 -> 2.40697 | J27: =J19-J26 -> 2.52201 | ... L27: =L19-L26 -> 2.78819
B28: Owner-Operator Savings (₹ Cr) | C28: 0.3 | D28: 0.3 | E28: 0.3 | F28: 0.3 | G28: 0.3 | H28: 0.3 | I28: 0.3 | J28: 0.3 | K28: 0.3 | L28: 0.3
B30: © 2025 Giritharan Chockalingam. All Rights Reserved. | This financial model and all associated intellectual property are proprietary and confidential.
B31: CONFIDENTIAL — For Board Approval Use Only | V3 Grand Madurai Investment Model v1.0 | Unauthorized reproduction or distribution is strictly prohibited.

Sheet 8. EBITDA & CF — P1
B1: EBITDA & Cash Flow — Phase 1
B2: V3 Grand Madurai • Confidential Board Material • February 2026
B4: EBITDA & CASH FLOW — PHASE 1
B5: P&L, Free Cash Flow & Debt Service · 55 Keys
B6: (₹ Crore) | C6: Year 1 | D6: Year 2 | E6: Year 3 | F6: Year 4 | G6: Year 5 | H6: Year 6 | I6: Year 7 | J6: Year 8 | K6: Year 9 | L6: Year 10
B7: Total Revenue | C7: 7.33 | D7: 8.73 | E7: 10.02 | F7: 10.97 | G7: 11.59 | H7: 12.17 | I7: 12.77 | J7: 13.41 | K7: 14.08 | L7: 14.79
B8: (-) Total Operating Expenses | C8: =C7*0.596 -> 4.36868 | D8: =D7*0.596 -> 5.20308 | E8: =E7*0.596 -> 5.97192 | F8: =F7*0.596 -> 6.53812 | G8: =G7*0.596 -> 6.90764 | H8: =H7*0.596 -> 7.25332 | I8: =I7*0.596 -> 7.61092 | J8: =J7*0.596 -> 7.99236 | ... L8: =L7*0.596 -> 8.81484
B10: EBITDA | C10: =C7-C8 -> 2.96132 | D10: =D7-D8 -> 3.52692 | E10: =E7-E8 -> 4.04808 | F10: =F7-F8 -> 4.43188 | G10: =G7-G8 -> 4.68236 | H10: =H7-H8 -> 4.91668 | I10: =I7-I8 -> 5.15908 | J10: =J7-J8 -> 5.41764 | ... L10: =L7-L8 -> 5.97516
B11: EBITDA Margin % | C11: =C10/C7 -> 0.404 | D11: =D10/D7 -> 0.404 | E11: =E10/E7 -> 0.404 | F11: =F10/F7 -> 0.404 | G11: =G10/G7 -> 0.404 | H11: =H10/H7 -> 0.404 | I11: =I10/I7 -> 0.404 | J11: =J10/J7 -> 0.404 | ... L11: =L10/L7 -> 0.404
B13: (-) Depreciation | C13: 1.04 | D13: 1.04 | E13: 1.04 | F13: 1.04 | G13: 1.04 | H13: 1.04 | I13: 1.04 | J13: 1.04 | K13: 1.04 | L13: 1.04
B14: EBIT | C14: =C10-C13 -> 1.92132 | D14: =D10-D13 -> 2.48692 | E14: =E10-E13 -> 3.00808 | F14: =F10-F13 -> 3.39188 | G14: =G10-G13 -> 3.64236 | H14: =H10-H13 -> 3.87668 | I14: =I10-I13 -> 4.11908 | J14: =J10-J13 -> 4.37764 | ... L14: =L10-L13 -> 4.93516
B15: (-) Interest Expense | C15: 1.43 | D15: 1.43 | E15: 1.43 | F15: 1.39 | G15: 1.34 | H15: 1.29 | I15: 1.24 | J15: 1.18 | K15: 1.11 | L15: 1.04
B16: Profit Before Tax (PBT) | C16: =C14-C15 -> 0.49132 | D16: =D14-D15 -> 1.05692 | E16: =E14-E15 -> 1.57808 | F16: =F14-F15 -> 2.00188 | G16: =G14-G15 -> 2.30236 | H16: =H14-H15 -> 2.58668 | I16: =I14-I15 -> 2.87908 | J16: =J14-J15 -> 3.19764 | ... L16: =L14-L15 -> 3.89516
B17: (-) Tax @ 25.17% | C17: =MAX(C16*0.2517,0) -> 0.12366524 | D17: =MAX(D16*0.2517,0) -> 0.26602676 | E17: =MAX(E16*0.2517,0) -> 0.39720274 | F17: =MAX(F16*0.2517,0) -> 0.5038732 | G17: =MAX(G16*0.2517,0) -> 0.57950401 | H17: =MAX(H16*0.2517,0) -> 0.65106736 | I17: =MAX(I16*0.2517,0) -> 0.72466444 | J17: =MAX(J16*0.2517,0) -> 0.80484599 | ... L17: =MAX(L16*0.2517,0) -> 0.98041177
B18: Profit After Tax (PAT) | C18: =C16-C17 -> 0.36765476 | D18: =D16-D17 -> 0.79089324 | E18: =E16-E17 -> 1.1808773 | F18: =F16-F17 -> 1.4980068 | G18: =G16-G17 -> 1.722856 | H18: =H16-H17 -> 1.9356126 | I18: =I16-I17 -> 2.1544156 | J18: =J16-J17 -> 2.392794 | ... L18: =L16-L17 -> 2.9147482
B20: FREE CASH FLOW
B21: PAT | C21: =C18 -> 0.36765476 | D21: =D18 -> 0.79089324 | E21: =E18 -> 1.1808773 | F21: =F18 -> 1.4980068 | G21: =G18 -> 1.722856 | H21: =H18 -> 1.9356126 | I21: =I18 -> 2.1544156 | J21: =J18 -> 2.392794 | ... L21: =L18 -> 2.9147482
B22: (+) Depreciation Add-back | C22: =C13 -> 1.04 | D22: =D13 -> 1.04 | E22: =E13 -> 1.04 | F22: =F13 -> 1.04 | G22: =G13 -> 1.04 | H22: =H13 -> 1.04 | I22: =I13 -> 1.04 | J22: =J13 -> 1.04 | ... L22: =L13 -> 1.04
B23: (-) Principal Repayment | C23: 0 | D23: 0 | E23: 0.41 | F23: 0.45 | G23: 0.5 | H23: 0.55 | I23: 0.6 | J23: 0.66 | K23: 0.73 | L23: 0.8
B24: (-) FF&E Reserve (3% from Yr 3) | C24: 0 | D24: 0 | E24: =E7*0.03 -> 0.3006 | F24: =F7*0.03 -> 0.3291 | G24: =G7*0.03 -> 0.3477 | H24: =H7*0.03 -> 0.3651 | I24: =I7*0.03 -> 0.3831 | J24: =J7*0.03 -> 0.4023 | K24: =K7*0.03 -> 0.4224 | L24: =L7*0.03 -> 0.4437
B25: (-) Working Capital Change | C25: =C8*30/365 -> 0.35906959 | D25: =D8*30/365 -> 0.42765041 | E25: =E8*30/365 -> 0.49084274 | F25: =F8*30/365 -> 0.53737973 | G25: =G8*30/365 -> 0.56775123 | H25: =H8*30/365 -> 0.59616329 | I25: =I8*30/365 -> 0.62555507 | J25: =J8*30/365 -> 0.6569063 | ... L25: =L8*30/365 -> 0.7245074
B27: FREE CASH FLOW TO EQUITY | C27: =C21+C22-C23-C24-C25 -> 1.0485852 | D27: =D21+D22-D23-D24-D25 -> 1.4032428 | E27: =E21+E22-E23-E24-E25 -> 1.0194345 | F27: =F21+F22-F23-F24-F25 -> 1.2215271 | G27: =G21+G22-G23-G24-G25 -> 1.3474048 | H27: =H21+H22-H23-H24-H25 -> 1.4643494 | I27: =I21+I22-I23-I24-I25 -> 1.5857605 | J27: =J21+J22-J23-J24-J25 -> 1.7135877 | ... L27: =L21+L22-L23-L24-L25 -> 1.9865408
B28: Cumulative FCF | C28: =C27-35.7 -> -34.651415 | D28: =C28+D27 -> -33.248172 | E28: =D28+E27 -> -32.228737 | F28: =E28+F27 -> -31.00721 | G28: =F28+G27 -> -29.659806 | H28: =G28+H27 -> -28.195456 | I28: =H28+I27 -> -26.609696 | J28: =I28+J27 -> -24.896108 | K28: =J28+K27 -> -23.05051 | L28: =K28+L27 -> -21.06397
B30: © 2025 Giritharan Chockalingam. All Rights Reserved. | This financial model and all associated intellectual property are proprietary and confidential.
B31: CONFIDENTIAL — For Board Approval Use Only | V3 Grand Madurai Investment Model v1.0 | Unauthorized reproduction or distribution is strictly prohibited.

Sheet 9. EBITDA & CF — Phased
B1: V3 GRAND MADURAI | EBITDA & CF — Phased | Base Case Analysis
B2: Prepared: February 2026 | Confidential - Board Use Only
B4: EBITDA & CASH FLOW — PHASED
B5: P&L, Free Cash Flow & Debt Service · 72 Keys
B6: (₹ Crore) | C6: Year 1 | D6: Year 2 | E6: Year 3 | F6: Year 4 | G6: Year 5 | H6: Year 6 | I6: Year 7 | J6: Year 8 | K6: Year 9 | L6: Year 10
B7: Total Revenue (Phased) | C7: 7.33 | D7: 8.73 | E7: 10.02 | F7: 12.64 | G7: 15.17 | H7: 15.93 | I7: 16.73 | J7: 17.57 | K7: 18.44 | L7: 19.37
B8: (-) Total Operating Expenses | C8: =C7*0.596 -> 4.36868 | D8: =D7*0.596 -> 5.20308 | E8: =E7*0.596 -> 5.97192 | F8: =F7*0.596 -> 7.53344 | G8: =G7*0.596 -> 9.04132 | H8: =H7*0.596 -> 9.49428 | I8: =I7*0.596 -> 9.97108 | J8: =J7*0.596 -> 10.47172 | ... L8: =L7*0.596 -> 11.54452
B10: EBITDA | C10: =C7-C8 -> 2.96132 | D10: =D7-D8 -> 3.52692 | E10: =E7-E8 -> 4.04808 | F10: =F7-F8 -> 5.10656 | G10: =G7-G8 -> 6.12868 | H10: =H7-H8 -> 6.43572 | I10: =I7-I8 -> 6.75892 | J10: =J7-J8 -> 7.09828 | ... L10: =L7-L8 -> 7.82548
B11: EBITDA Margin % | C11: =C10/C7 -> 0.404 | D11: =D10/D7 -> 0.404 | E11: =E10/E7 -> 0.404 | F11: =F10/F7 -> 0.404 | G11: =G10/G7 -> 0.404 | H11: =H10/H7 -> 0.404 | I11: =I10/I7 -> 0.404 | J11: =J10/J7 -> 0.404 | ... L11: =L10/L7 -> 0.404
B13: (-) Depreciation | C13: 1.04 | D13: 1.04 | E13: 1.04 | F13: 1.33 | G13: 1.33 | H13: 1.33 | I13: 1.33 | J13: 1.33 | K13: 1.33 | L13: 1.33
B14: EBIT | C14: =C10-C13 -> 1.92132 | D14: =D10-D13 -> 2.48692 | E14: =E10-E13 -> 3.00808 | F14: =F10-F13 -> 3.77656 | G14: =G10-G13 -> 4.79868 | H14: =H10-H13 -> 5.10572 | I14: =I10-I13 -> 5.42892 | J14: =J10-J13 -> 5.76828 | ... L14: =L10-L13 -> 6.49548
B15: (-) Interest Expense | C15: 1.43 | D15: 1.43 | E15: 1.43 | F15: 1.68 | G15: 1.63 | H15: 1.58 | I15: 1.52 | J15: 1.45 | K15: 1.37 | L15: 1.29
B16: Profit Before Tax (PBT) | C16: =C14-C15 -> 0.49132 | D16: =D14-D15 -> 1.05692 | E16: =E14-E15 -> 1.57808 | F16: =F14-F15 -> 2.09656 | G16: =G14-G15 -> 3.16868 | H16: =H14-H15 -> 3.52572 | I16: =I14-I15 -> 3.90892 | J16: =J14-J15 -> 4.31828 | ... L16: =L14-L15 -> 5.20548
B17: (-) Tax @ 25.17% | C17: =MAX(C16*0.2517,0) -> 0.12366524 | D17: =MAX(D16*0.2517,0) -> 0.26602676 | E17: =MAX(E16*0.2517,0) -> 0.39720274 | F17: =MAX(F16*0.2517,0) -> 0.52770415 | G17: =MAX(G16*0.2517,0) -> 0.79755676 | H17: =MAX(H16*0.2517,0) -> 0.88742372 | I17: =MAX(I16*0.2517,0) -> 0.98387516 | J17: =MAX(J16*0.2517,0) -> 1.0869111 | ... L17: =MAX(L16*0.2517,0) -> 1.3102193
B18: Profit After Tax (PAT) | C18: =C16-C17 -> 0.36765476 | D18: =D16-D17 -> 0.79089324 | E18: =E16-E17 -> 1.1808773 | F18: =F16-F17 -> 1.5688558 | G18: =G16-G17 -> 2.3711232 | H18: =H16-H17 -> 2.6382963 | I18: =I16-I17 -> 2.9250448 | J18: =J16-J17 -> 3.2313689 | ... L18: =L16-L17 -> 3.8952607
B20: FREE CASH FLOW
B21: PAT | C21: =C18 -> 0.36765476 | D21: =D18 -> 0.79089324 | E21: =E18 -> 1.1808773 | F21: =F18 -> 1.5688558 | G21: =G18 -> 2.3711232 | H21: =H18 -> 2.6382963 | I21: =I18 -> 2.9250448 | J21: =J18 -> 3.2313689 | ... L21: =L18 -> 3.8952607
B22: (+) Depreciation | C22: =C13 -> 1.04 | D22: =D13 -> 1.04 | E22: =E13 -> 1.04 | F22: =F13 -> 1.33 | G22: =G13 -> 1.33 | H22: =H13 -> 1.33 | I22: =I13 -> 1.33 | J22: =J13 -> 1.33 | ... L22: =L13 -> 1.33
B23: (-) Phase 2 CAPEX | C23: 0 | D23: 0 | E23: 0 | F23: 7.3 | G23: 0 | H23: 0 | I23: 0 | J23: 0 | K23: 0 | L23: 0
B24: (-) Principal Repayment | C24: 0 | D24: 0 | E24: 0.41 | F24: 0.45 | G24: 0.5 | H24: 0.63 | I24: 0.7 | J24: 0.77 | K24: 0.84 | L24: 0.93
B25: (-) FF&E Reserve (3% from Yr 3) | C25: 0 | D25: 0 | E25: =E7*0.03 -> 0.3006 | F25: =F7*0.03 -> 0.3792 | G25: =G7*0.03 -> 0.4551 | H25: =H7*0.03 -> 0.4779 | I25: =I7*0.03 -> 0.5019 | J25: =J7*0.03 -> 0.5271 | K25: =K7*0.03 -> 0.5532 | L25: =L7*0.03 -> 0.5811
B26: (-) Working Capital Change | C26: =C8*30/365 -> 0.35906959 | D26: =D8*30/365 -> 0.42765041 | E26: =E8*30/365 -> 0.49084274 | F26: =F8*30/365 -> 0.61918685 | G26: =G8*30/365 -> 0.74312219 | H26: =H8*30/365 -> 0.78035178 | I26: =I8*30/365 -> 0.81954082 | J26: =J8*30/365 -> 0.86068932 | ... L26: =L8*30/365 -> 0.94886466
B28: FREE CASH FLOW TO EQUITY | C28: =C21+C22-C23-C24-C25-C26 -> 1.0485852 | D28: =D21+D22-D23-D24-D25-D26 -> 1.4032428 | E28: =E21+E22-E23-E24-E25-E26 -> 1.0194345 | F28: =F21+F22-F23-F24-F25-F26 -> -5.849531 | G28: =G21+G22-G23-G24-G25-G26 -> 2.0029011 | H28: =H21+H22-H23-H24-H25-H26 -> 2.0800445 | I28: =I21+I22-I23-I24-I25-I26 -> 2.233604 | J28: =J21+J22-J23-J24-J25-J26 -> 2.4035796 | ... L28: =L21+L22-L23-L24-L25-L26 -> 2.765296
B29: Cumulative FCF (net of ₹43.0 Cr total) | C29: =C28-35.7 -> -34.651415 | D29: =C29+D28 -> -33.248172 | E29: =D29+E28 -> -32.228737 | F29: =E29+F28 -> -38.078268 | G29: =F29+G28 -> -36.075367 | H29: =G29+H28 -> -33.995323 | I29: =H29+I28 -> -31.761719 | J29: =I29+J28 -> -29.358139 | K29: =J29+K28 -> -26.770401 | L29: =K29+L28 -> -24.005105
B31: © 2025 Giritharan Chockalingam. All Rights Reserved. | This financial model and all associated intellectual property are proprietary and confidential.
B32: CONFIDENTIAL — For Board Approval Use Only | V3 Grand Madurai Investment Model v1.0 | Unauthorized reproduction or distribution is strictly prohibited.

Sheet 10. Returns Analysis
B2: RETURNS ANALYSIS
B3: IRR, NPV, Payback & Sensitivity · Phase 1 vs Phased
B5: PHASE 1 ONLY (55 KEYS) — ₹35.7 Cr Investment | O5: MULTI-VARIABLE SENSITIVITY ANALYSIS
C6: Year 0 | D6: Year 1 | E6: Year 2 | F6: Year 3 | G6: Year 4 | H6: Year 5 | I6: Year 6 | J6: Year 7 | K6: Year 8 | L6: Year 9 | M6: Year 10
B7: EBITDA | C7: 0 | D7: 2.93 | E7: 3.53 | F7: 4.05 | G7: 4.43 | H7: 4.48 | I7: 4.87 | J7: 5.3 | K7: 5.58 | L7: 5.84 | M7: 6.12 | O7: NPV Sensitivity to Key Variables (₹ Cr)
B8: (included in EBITDA — net of reserves) | C8: 0 | D8: 0 | E8: 0 | F8: 0 | G8: 0 | H8: 0 | I8: 0 | J8: 0 | K8: 0 | L8: 0 | M8: 0
B9: Exit Value (13.4x Year 10 EBITDA) | C9: 0 | D9: 0 | E9: 0 | F9: 0 | G9: 0 | H9: 0 | I9: 0 | J9: 0 | K9: 0 | L9: 0 | M9: 82.1 | O9: Occupancy ↓ / ADR → | P9: -10% | Q9: Base | R9: +10% | S9: +15%
B10: Net Cash Flow | C10: -35.7 | D10: =D7-D8+D9 -> 2.93 | E10: =E7-E8+E9 -> 3.53 | F10: =F7-F8+F9 -> 4.05 | G10: =G7-G8+G9 -> 4.43 | H10: =H7-H8+H9 -> 4.48 | I10: =I7-I8+I9 -> 4.87 | J10: =J7-J8+J9 -> 5.3 | K10: =K7-K8+K9 -> 5.58 | ... M10: =M7-M8+M9 -> 88.22 | O10: -10% | P10: -2.5 | Q10: 3.2 | R10: 9.8 | S10: 13.2
O11: -5% | P11: 2.1 | Q11: 7.5 | R11: 14.2 | S11: 18.5
B12: KEY METRICS | O12: Base (78%) | P12: 6.1 | Q12: 15.9 | R12: 22.4 | S12: 27.8
B13: 10-Year IRR | C13: =IRR(C10:M10) -> 0.17603612 | D13: ⚠️ MARGINAL (17.6% vs 17.5%) | O13: +5% | P13: 10.8 | Q13: 21.2 | R13: 28.5 | S13: 34.1
B14: NPV @ 17.5% | C14: =NPV(0.175,D10:M10)+C10 -> 0.22650427 | O14: +10% | P14: 15.2 | Q14: 26.8 | R14: 35.2 | S14: 41.8
B15: Return Multiple | C15: =SUM(D10:M10)/(-C10) -> 3.619888 | O15: +15% | P15: 19.5 | Q15: 32.1 | R15: 42.5 | S15: 50.2
B16: Payback Period (Years) | C16: 9.8 | D16: (Extended due to realistic occupancy)
B17: Exit Value | C17: =M9 -> 82.1
B18: Hurdle Rate | C18: 0.175 | D18: (Risk-Adjusted WACC)
B20: PHASED EXPANSION (55→72 KEYS) — ₹43.0 Cr Total Investment | O20: CAPEX ↓ / Margin → | P20: -2% | Q20: Base (40.4%) | R20: +2% | S20: +4%
C21: Year 0 | D21: Year 1 | E21: Year 2 | F21: Year 3 | G21: Year 4 | H21: Year 5 | I21: Year 6 | J21: Year 7 | K21: Year 8 | L21: Year 9 | M21: Year 10 | O21: +20% | P21: 0.112 | Q21: 0.135 | R21: 0.158 | S21: 0.181
B22: EBITDA | C22: 0 | D22: 2.93 | E22: 3.53 | F22: 4.05 | G22: 5.11 | H22: 6.07 | I22: 6.44 | J22: 6.88 | K22: 7.22 | L22: 7.68 | M22: 8.21 | O22: +10% | P22: 0.131 | Q22: 0.153 | R22: 0.176 | S22: 0.199
B23: (included in EBITDA — net of reserves) | C23: 0 | D23: 0 | E23: 0 | F23: 0 | G23: 0 | H23: 0 | I23: 0 | J23: 0 | K23: 0 | L23: 0 | M23: 0 | O23: Base (₹43 Cr) | P23: 0.148 | Q23: 0.178 | R23: 0.201 | S23: 0.225
B24: (-) Phase 2 CAPEX | C24: 0 | D24: 0 | E24: 0 | F24: 0 | G24: -7.3 | H24: 0 | I24: 0 | J24: 0 | K24: 0 | L24: 0 | M24: 0 | O24: -5% | P24: 0.162 | Q24: 0.192 | R24: 0.218 | S24: 0.242
B25: Exit Value (10.5x Year 10 EBITDA) | C25: 0 | D25: 0 | E25: 0 | F25: 0 | G25: 0 | H25: 0 | I25: 0 | J25: 0 | K25: 0 | L25: 0 | M25: 86.2 | O25: -10% | P25: 0.178 | Q25: 0.212 | R25: 0.238 | S25: 0.268
B26: Net Cash Flow | C26: -35.7 | D26: =D22-D23+D24+D25 -> 2.93 | E26: =E22-E23+E24+E25 -> 3.53 | F26: =F22-F23+F24+F25 -> 4.05 | G26: =G22-G23+G24+G25 -> -2.19 | H26: =H22-H23+H24+H25 -> 6.07 | I26: =I22-I23+I24+I25 -> 6.44 | J26: =J22-J23+J24+J25 -> 6.88 | K26: =K22-K23+K24+K25 -> 7.22 | ... M26: =M22-M23+M24+M25 -> 94.41
B28: KEY METRICS
B29: 10-Year IRR | C29: =IRR(C26:M26) -> 0.17797788 | D29: ⚠️ MARGINAL (17.8% vs 17.5%)
B30: NPV @ 17.5% | C30: =NPV(0.175,D26:M26)+C26 -> 0.68732818 | O30: Rev Growth ↓ / OpEx → | P30: +2% | Q30: Base | R30: -2% | S30: -4%
B31: Return Multiple | C31: =SUM(D26:M26)/(-C26) -> 3.8380952 | O31: -2% | P31: 9.8 | Q31: 8.9 | R31: 8.1 | S31: 7.5
B32: Payback Period (Years) | C32: 9.2 | D32: (~1.5 years longer than original estimate)
B33: Exit Value (12x EBITDA) | C33: =M25 -> 86.2 | O33: Base (5%) | P33: 8.6 | Q33: 7.8 | R33: 7.1 | S33: 6.5
O34: +2% | P34: 7.5 | Q34: 6.8 | R34: 6.2 | S34: 5.7
B35: TERMINAL VALUE — GORDON GROWTH MODEL | O35: +4% | P35: 6.5 | Q35: 5.9 | R35: 5.4 | S35: 5
B36: Year 10 EBITDA (Phased) | C36: 8.21
B37: Terminal Growth Rate | C37: 0.04
B38: WACC | C38: 0.175
B39: Terminal Value (Gordon Growth) | C39: =C36*(1+C37)/(C38-C37) -> 63.247407
B40: PV of Terminal Value | C40: =C39/(1+C38)^10 -> 12.608519 | O40: KEY ASSUMPTIONS (BASE CASE)
B41: Implied Exit Multiple | C41: =C39/C36 -> 7.7037037
O42: Assumption | P42: Value
B43: ⚠️ CRITICAL MODEL UPDATES - REALISTIC ASSUMPTIONS | O43: Total Investment | P43: ₹43.0 Cr
B44: Original Optimistic vs. Revised Reality-Based Model | C44: Stabilized ADR (₹) → | D44: 3500 | E44: 4000 | F44: 4500 | G44: 5000 | H44: 5500 | I44: 6000 | J44: 6500 | O44: Phase 1 Keys | P44: 55
B45: Occupancy ↓ | C45: 0.6 | D45: 0.031 | E45: 0.045 | F45: 0.058 | G45: 0.069 | H45: 0.079 | I45: 0.089 | J45: 0.097 | O45: Phase 2 Keys | P45: +17 (Month 43)
B46: Assumption Changed | C46: Impact | D46: Board Implication | E46: 0.054 | F46: 0.066 | G46: 0.077 | H46: 0.088 | I46: 0.097 | J46: 0.106 | O46: Stabilized Occupancy | P46: 78%
B47: Hurdle Rate / Discount | C47: 12.0% → 17.5% (+5.5 pp) | D47: Proper WACC: Indian hotel comps + country/size/project risk | E47: 0.062 | F47: 0.074 | G47: 0.086 | H47: 0.096 | I47: 0.105 | J47: 0.114 | O47: Stabilized ADR | P47: ₹5,000
B48: Year 1 Occupancy | C48: 65% → 40% (-25 pp) | D48: Realistic new hotel ramp (industry: 30-40% Y1, 50-55% Y2) | E48: 0.069 | F48: 0.082 | G48: 0.093 | H48: 0.103 | I48: 0.113 | J48: 0.122 | O48: EBITDA Margin | P48: 40.4%
B49: Year 2 Occupancy | C49: 70% → 60% (-10 pp) | D49: Gradual market penetration vs instant success | E49: 0.073 | F49: 0.086 | G49: 0.097 | H49: 0.108 | I49: 0.118 | J49: 0.126 | O49: Exit Multiple | P49: 12x EBITDA
B50: Anchor MOU Realization | C50: 100% Day 1 → 70%/85%/100% | D50: Phased partnership ramp-up (realistic activation) | E50: 0.076 | F50: 0.089 | G50: 0.1 | H50: 0.111 | I50: 0.12 | J50: 0.129 | O50: Hurdle Rate | P50: 12%
C51: 0.85 | D51: 0.068 | E51: 0.082 | F51: 0.095 | G51: 0.107 | H51: 0.117 | I51: 0.127 | J51: 0.136 | O51: Project Life | P51: 10 years
B52: FINANCIAL IMPACT OF REALISTIC ASSUMPTIONS | O52: Phase 2 Trigger | P52: Yes (8/8 gates)
B53: Phase 1 NPV @ 17.5% | C53: ₹15.9 Cr → ₹0.23 Cr (-98.5%) | D53: Project now MARGINALLY viable. Near-zero value creation
B54: Phased NPV @ 17.5% | C54: ₹15.9 Cr → ₹0.69 Cr (-95.7%) | D54: Returns compressed. Minimal margin of safety | E54: Phased | F54: Status
B55: IRR Margin Over Hurdle | C55: Phase 1: 0.1 pp | Phased: 0.3 pp | D55: ⚠️ CRITICAL: No margin for error. Any variance fails hurdle | E55: =C29 -> 0.17797788 | F55: =IF(C13>0.12,"✓ PASS","✗ FAIL") -> ✓ PASS
B56: Payback Period | C56: 7.8 yrs → 9-10 yrs (+2 yrs) | D56: Extended capital recovery = higher risk exposure | E56: 7.8 years | F56: ✓ PASS
B57: Return Multiple | C57: >2.0x | D57: =C15 -> 3.619888 | E57: =C31 -> 3.8380952 | F57: =IF(C15>2,"✓ PASS","✗ FAIL") -> ✓ PASS
B58: ⚠️ BOARD RECOMMENDATION - REVISED | C58: >₹0 | D58: =C14 -> 0.22650427 | E58: =C30 -> 0.68732818 | F58: =IF(C14>0,"✓ PASS","✗ FAIL") -> ✓ PASS
B59: Project NO LONGER meets 'Strong Buy' criteria under realistic assumptions. Recommendation: CONDITIONAL APPROVAL pending 3-star 'Lite' alternative OR DEFER until market improves. Current 4-star positioning over-specified for Tier-II demand.
B60: © 2025 Giritharan Chockalingam. All Rights Reserved. | This financial model and all associated intellectual property are proprietary and confidential.
B61: CONFIDENTIAL — For Board Approval Use Only | V3 Grand Madurai Investment Model v1.0 | Unauthorized reproduction or distribution is strictly prohibited.
B62: BREAK-EVEN ANALYSIS
B64: Break-Even Metric | C64: Phase 1 | D64: Phased | E64: Notes
B65: Break-Even Occupancy (at Base ADR) | C65: 52.3% | D65: 48.7% | E65: OpEx coverage only
B66: Break-Even ADR (at Base Occ) | C66: ₹3,240 | D66: ₹3,180 | E66: OpEx coverage only
B67: Cash Break-Even Occupancy | C67: 61.5% | D67: 57.2% | E67: OpEx + Debt Service
B68: IRR = 12% Occupancy | C68: 68.5% | D68: 71.8% | E68: Hurdle rate achievement
B69: IRR = 12% ADR | C69: ₹4,280 | D69: ₹4,520 | E69: Hurdle rate achievement
B70: Zero NPV Occupancy | C70: 64.2% | D70: 62.8% | E70: Value breakeven
B71: Exit Multiple for IRR = 15% | C71: 10.2x | D71: 9.8x | E71: Sensitivity to exit
B77: NPV PROFILE BY DISCOUNT RATE
B79: Discount Rate | C79: Phase 1 NPV (₹ Cr) | D79: Phased NPV (₹ Cr) | E79: Spread (₹ Cr)
B80: 8% | C80: 28.5 | D80: 32.1 | E80: 3.6
B81: 10% | C81: 21.2 | D81: 23.8 | E81: 2.6
B82: 12% | C82: 15.6 | D82: 17.1 | E82: 1.5
B83: 14% | C83: 11.2 | D83: 12.1 | E83: 0.9
B84: 16% | C84: 7.8 | D84: 8.3 | E84: 0.5
B85: 17.8% (IRR) | C85: 5 | D85: 5.2 | E85: 0.2
B86: 18% | C86: 4.9 | D86: 5 | E86: 0.1
B87: 20% | C87: 2.5 | D87: 2.3 | E87: -0.2
B92: INVESTMENT DECISION MATRIX
B94: Metric | C94: Phase 1 | D94: Phased | E94: Difference | F94: Winner | G94: Weight | H94: Score
B95: IRR | C95: 17.6% | D95: 17.8% | E95: +0.2% | F95: Phased | G95: 40% | H95: 1
B96: NPV | C96: ₹15.6 Cr | D96: ₹17.1 Cr | E96: +₹1.5 Cr | F96: Phased | G96: 30% | H96: 1
B97: Return Multiple | C97: 3.62x | D97: 3.84x | E97: +0.22x | F97: Phased | G97: 15% | H97: 1
B98: Payback Period | C98: 8.2 yrs | D98: 7.8 yrs | E98: -0.4 yrs | F98: Phased | G98: 10% | H98: 1
B99: Risk/Complexity | C99: Low | D99: Medium | E99: +1 level | F99: Phase 1 | G99: 5% | H99: 0
B100: TOTAL WEIGHTED SCORE | F100: Phased Wins | G100: 95% | H100: =0.4*H95+0.3*H96+0.15*H97+0.1*H98+0.05*H99 -> 0.95

Sheet 11. Scenario Stress Test
B1: V3 GRAND MADURAI | Scenario Stress Test | Base Case Analysis
B2: Prepared: February 2026 | Confidential - Board Use Only
B3: 📊 MODEL UPDATED: Feb 2026 - Now using 17.5% hurdle rate (proper WACC) vs. prior 12%
B4: Bear case occupancy updated to realistic ramp: 35-40% Y1, 50-55% Y2, 60-65% Y3+
B7: SCENARIO STRESS TEST
B8: Bear (20%) · Base (60%) · Bull (20%) · Probability-Weighted
B10: SCENARIO COMPARISON
C11: Bear Case | D11: Base Case | E11: Bull Case | F11: Expected
B12: Probability Weight | C12: 0.2 | D12: 0.6 | E12: 0.2
B14: KEY ASSUMPTIONS
B15: Stabilized Occupancy | C15: 35-40% Y1→60-65% Y3+ | D15: 75-78% | E15: 80-83%
B16: Stabilized ADR (₹) | C16: ₹4,500 | D16: ₹5,000 | E16: ₹6,000
B17: EBITDA Margin | C17: 0.36 | D17: 0.4 | E17: 0.42
B18: MOU Realization | C18: 60% of target | D18: 100% of target | E18: 120%+ of target
B19: Phase 2 Triggered? | C19: No (stays at 55 keys) | D19: Yes (72 keys) | E19: Yes (72 keys)
B20: Competitive Risk | C20: Residency Tower expands | D20: Status quo | E20: No new entrants
B22: RETURNS METRICS
B23: IRR (10-Year) | C23: 0.143 | D23: 0.178 | E23: 0.229 | F23: =C23*C12+D23*D12+E23*E12 -> 0.1812
B24: NPV @ 17.5% | C24: -2 | D24: 0.69 | E24: 18.5 | F24: 3.5
B25: Payback Period (Years) | C25: ⚠️ MARGINAL (9.5-10.0 yrs) | D25: ✅ PASS (9.2 yrs) | E25: 6.4 | F25: ✅ PASS (8.8 yrs)
B26: Return Multiple | C26: ❌ FAIL (1.95x < 2.0x) | D26: 2.71 | E26: 3.4 | F26: =C26*C12+D26*D12+E26*E12 -> #VALUE!
B27: Year 10 EBITDA (₹ Cr) | C27: 4.8 | D27: 7.83 | E27: 11.2 | F27: =C27*C12+D27*D12+E27*E12 -> 7.898
B28: Exit Value (₹ Cr) | C28: 57.6 | D28: 93.9 | E28: 134.4 | F28: =C28*C12+D28*D12+E28*E12 -> 94.74
B30: PROBABILITY-WEIGHTED EXPECTED IRR | C30: =F23 -> 0.1812 | D30: (vs. 12% hurdle rate)
B32: BEAR CASE SAFETY NET
B33: Even in bear case, IRR of 14.3% exceeds 12% hurdle rate
B34: IRR > 17.5% (Proper Hurdle) | C34: ❌ FAIL (14.3% < 17.5%) | D34: ⚠️ MARGINAL (17.8% vs 17.5%) | E34: ✅ PASS (22.9% >> 17.5%) | F34: ⚠️ MARGINAL (17.8% vs 17.5%)
B35: Anchor partnerships provide 8-11% occupancy floor
B36: Phase 2 NOT triggered in bear case — limits downside exposure
B37: Medical tourism provides counter-cyclical demand stability
B38: Owner-operator model saves ₹30L/year vs. external GM
B40: 10-YEAR REVENUE TRAJECTORY BY SCENARIO (₹ Crore)
C41: Year 1 | D41: Year 2 | E41: Year 3 | F41: Year 4 | G41: Year 5 | H41: Year 6 | I41: Year 7 | J41: Year 8 | K41: Year 9 | L41: Year 10
B42: Bear Case (55 keys) | C42: 5.5 | D42: 6.4 | E42: 7.2 | F42: 7.8 | G42: 8.2 | H42: 8.61 | I42: 9.04 | J42: 9.49 | K42: 9.97 | L42: 10.47
B43: Base Case (72 keys) | C43: 7.33 | D43: 8.73 | E43: 10.02 | F43: 12.64 | G43: 15.17 | H43: 15.93 | I43: 16.73 | J43: 17.57 | K43: 18.44 | L43: 19.37
B44: Bull Case (72 keys) | C44: 8.9 | D44: 10.8 | E44: 12.6 | F44: 16.4 | G44: 20.1 | H44: 21.3 | I44: 22.6 | J44: 23.95 | K44: 25.39 | L44: 26.91
B46: © 2025 Giritharan Chockalingam. All Rights Reserved. | This financial model and all associated intellectual property are proprietary and confidential.
B47: CONFIDENTIAL — For Board Approval Use Only | V3 Grand Madurai Investment Model v1.0 | Unauthorized reproduction or distribution is strictly prohibited.
B51: DECISION CRITERIA BY SCENARIO
B52: Criterion | C52: Bear | D52: Base | E52: Bull
B53: IRR > 12% | C53: ✅ | D53: ✅ | E53: ✅
B54: NPV > ₹0 | C54: ❌ FAIL (₹-2.0 Cr) | D54: ✅ PASS (₹0.69 Cr) | E54: ✅ PASS (₹18.5 Cr) | F54: ✅ PASS (₹3.5 Cr)
B55: Payback < 10 yrs | C55: ✅ | D55: ✅ | E55: ✅
B56: Multiple > 2x | C56: ✅ | D56: ✅ | E56: ✅
B57: EBITDA > 35% | C57: ✅ | D57: ✅ | E57: ✅
B59: ⚠️ CRITICAL IMPLICATIONS OF RESTRUCTURED MODEL
B60: • Bear case now fails on 3 criteria: NPV negative (₹-2.0 Cr), IRR below hurdle (14.3% < 17.5%), Return Multiple < 2.0x
B61: • Base case marginally viable: NPV only ₹0.69 Cr (was ₹15.9 Cr @ 12%), IRR margin only 0.3 percentage points above hurdle
B62: • Expected NPV dropped 77% from ₹15.0 Cr to ₹3.5 Cr due to corrected 17.5% hurdle rate
B63: • Risk profile: HIGH - Any underperformance vs Base case results in investment hurdle failures
B64: • Recommendation: Conditional approval with mandatory performance gates and cost controls
B69: SCENARIO RECOMMENDATIONS
B70: Bear | C70: ❌ NOT VIABLE - Fails multiple hurdles
B71: Base | C71: Recommended - Balanced risk/return | D71: ⚠️ CONDITIONAL - Marginal returns
B72: Bull | C72: Optimistic - High return, low probability

Sheet 12. Operating Model Decision
B1: Operating Model Decision Framework
B2: V3 Grand Madurai • Confidential Board Material • February 2026
B4: OPERATING MODEL DECISION | P4: CF Helpers (hidden)
B5: Independent vs IHG vs IHCL Taj vs Marriott vs Lemon Tree | P5: -43 | Q5: =C31 -> 2.96132 | R5: =D31 -> 3.52692 | S5: =E31 -> 4.04808 | T5: =F31 -> 5.10656 | U5: =G31-7.3 -> -1.17132 | V5: =H31 -> 6.43572 | W5: =I31 -> 6.75892 | X5: =J31 -> 7.09828 | Y5: =K31 -> 7.44976 | Z5: =L31+L31*12 -> 101.73124
P6: -43.9 | Q6: =C37 -> 2.5614443 | R6: =D37 -> 3.0678593 | S6: =E37 -> 3.5344845 | T6: =F37 -> 4.482204 | U6: =G37-7.3 -> -1.9026317 | V6: =H37 -> 5.6722793 | W6: =I37 -> 5.9616593 | X6: =J37 -> 6.2655083 | Y6: =K37 -> 6.580209 | Z6: =L37+L37*12 -> 89.915972
P7: -45 | Q7: =C47 -> 1.9882418 | R7: =D47 -> 2.4634858 | S7: =E47 -> 2.9013892 | T7: =F47 -> 3.7907744 | U7: =G47-7.3 -> -2.6503918 | V7: =H47 -> 4.9075978 | W7: =I47 -> 5.1791658 | X7: =J47 -> 5.4643122 | Y7: =K47 -> 5.7596424 | Z7: =L47+L47*12 -> 78.979423
B8: OPERATING MODEL COMPARISON | P8: -45.75 | Q8: =C56 -> 1.6780074 | R8: =D56 -> 2.1083226 | S8: =E56 -> 2.5048274 | T8: =F56 -> 3.3101315 | U8: =G56-7.3 -> -3.2122274 | V8: =H56 -> 4.3213722 | W8: =I56 -> 4.5672666 | X8: =J56 -> 4.8254558 | Y8: =K56 -> 5.0928659 | Z8: =L56+L56*12 -> 69.923336
B9: Dimension | C9: 1. Independent Owner-Operated (Selected ✓) | D9: 2. IHG / Wyndham Franchise | E9: 3. IHCL (Taj) / ITC Mgmt Contract | F9: 4. Marriott / Hyatt Mgmt Contract | G9: 5. Lemon Tree / Keys Select (Franchise-Lite) | P9: -43.45 | Q9: =C63 -> 2.323323 | R9: =D63 -> 2.775663 | S9: =E63 -> 3.192462 | T9: =F63 -> 4.038984 | U9: =G63-7.3 -> -2.443573 | V9: =H63 -> 5.101983 | W9: =I63 -> 5.360463 | X9: =J63 -> 5.631867 | Y9: =K63 -> 5.912964 | Z9: =L63+L63*12 -> 80.774811
B10: Minimum Key Requirement | C10: No minimum — any size | D10: IHG Holiday Inn Express: 75+ keys; Wyndham Ramada: 50+ keys — 72 keys QUALIFIES | E10: Taj/Vivanta: 100+ keys; Ginger (IHCL budget): 80+ keys — 72 keys DOES NOT QUALIFY for Taj; marginal for Ginger | F10: Marriott Courtyard/Fairfield: 100+ keys; Hyatt Place: 100+ keys — 72 keys DOES NOT QUALIFY | G10: Lemon Tree: 50+ keys; Keys Select: 40+ keys — 72 keys QUALIFIES easily
B11: Fee Structure | C11: ₹0 — Zero recurring fees to any brand or operator | D11: IHG: 5% royalty + 2.5% marketing + 1% reservation = 8.5% of gross room revenue; Wyndham: 4.5% royalty + 2% marketing = 6.5% | E11: IHCL base fee: 2.5% of total revenue + incentive fee: 8-10% of GOP (Gross Operating Profit) + technical services: 1-2% of revenue + marketing: 2% | F11: Marriott base: 3% of total revenue + incentive: 8-10% of GOP + system/loyalty: 5.5% of room revenue + marketing: 1.5% of revenue | G11: Lemon Tree: 3% of revenue + 1.5% marketing = 4.5% total; Keys Select: similar structure
B12: Total Fee Burden (@ ₹15 Cr stabilized revenue) | C12: ₹0 per year | D12: ₹0.98 - 1.28 Cr/year (6.5-8.5% of room revenue ≈ 70% of ₹15 Cr) | E12: ₹1.47 - 1.98 Cr/year (base 2.5% + incentive 8% of 40% GOP + tech/mktg 3%) | F12: ₹1.80 - 2.25 Cr/year (base 3% + incentive 10% of GOP + system 5.5% room rev + mktg) | G12: ₹0.68 Cr/year (4.5% of total revenue)
B13: Effective EBITDA Margin (after all fees) | C13: 40.4% — full operating profit retained | D13: 33 - 36% (margin eroded by 4-7% from fees on gross revenue) | E13: 30 - 33% (base + incentive + technical fees compound heavily) | F13: 27 - 31% (Marriott has highest all-in fee load among global chains) | G13: 36 - 38% (lightest fee structure among branded options)
B14: Upfront Brand Investment (PIP / Standards) | C14: ₹0 — build to own standards | D14: ₹0.60 - 1.20 Cr PIP compliance (technology systems, signage, amenity standards, brand-mandated F&B concepts) | E14: ₹1.50 - 2.50 Cr (Taj/Vivanta design mandates, imported finishes, brand F&B kitchen specs, central HVAC upgrades) | F14: ₹2.00 - 3.50 Cr (Marriott MEP specs, Bonvoy technology integration, brand-approved FF&E suppliers, F&B design) | G14: ₹0.30 - 0.60 Cr (lighter standards, Indian supply chain, minimal technology mandates)
B15: Contract Term & Exit Provisions | C15: None — full operational freedom, can brand later | D15: IHG: 10-year initial + 5-year renewal; Wyndham: 10-15 years; exit penalty: 3-5 years of fees (₹3-6 Cr); PIP refresh every 5 years | E15: IHCL: 15-20 years; exit requires 24-month notice + liquidated damages of 2-3 years fees; change of ownership triggers consent clause | F15: Marriott: 20-25 years (longest in industry); exit penalty: up to 5 years of projected fees (₹9-11 Cr); performance test: only after Year 5, narrow cure periods | G15: Lemon Tree: 8-10 years; more flexible exit with 12-month notice; renewal at mutual option
B16: Distribution & Loyalty Program | C16: Zero — 100% reliance on OTAs (MakeMyTrip, Booking.com, Goibibo, Agoda) + direct; build own website/app over time | D16: IHG Rewards: 100M+ members globally, ~2M India; Wyndham Rewards: 110M members; GDS connectivity; corporate RFP access | E16: IHCL Epicure + Taj InnerCircle: 3.5M+ members; strong domestic corporate loyalty; government/PSU preferred lists | F16: Marriott Bonvoy: 200M+ members globally, ~8M India — STRONGEST loyalty program; dominant on global corporate RFP mandates | G16: Lemon Tree Smiles: 1M+ members; growing domestic base; limited international reach; strong OTA presence
B17: Expected Occupancy / ADR Impact vs Independent | C17: Baseline: 78% stabilized, ₹5,000 ADR (model assumptions) | D17: +3-5% occupancy, +₹200-400 ADR in Tier-2; net benefit diluted by fees; stronger effect in metro cities than Madurai | E17: +5-8% occupancy, +₹800-1,200 ADR (Taj/Vivanta brand commands premium); BUT 72 keys disqualifies for Taj-branded property | F17: +5-10% occupancy, +₹500-1,000 ADR (Bonvoy drives demand); BUT 72 keys below Marriott minimum; Madurai has limited Bonvoy traffic | G17: +2-4% occupancy, +₹100-200 ADR; Lemon Tree well-known in India but positioned lower (₹3,000-4,500 ADR range)
B18: Owner Control & Decision Authority | C18: Full — owner sets pricing, selects staff, controls brand identity, procurement, renovation timing, and operational strategy | D18: Moderate — owner operates but must comply with brand standards (amenities, technology, design); owner selects GM subject to brand approval | E18: Low — IHCL appoints GM and senior management; owner has limited say on hiring, pricing, procurement; monthly reporting mandated | F18: Very Low — Marriott controls all ops, appoints GM, sets pricing via revenue management, mandates approved vendor lists, requires brand-approved capex | G18: Moderate-High — owner operates; Lemon Tree provides SOP framework + training; owner retains pricing and staffing control
B19: Madurai Market Fit (Tier-2 Assessment) | C19: STRONGEST FIT — No direct 4-star competitor; ₹4,000-5,000 ADR sweet spot; owner knows local demand drivers; medical/corporate MOUs replace brand distribution | D19: MODERATE FIT — Holiday Inn Express works in Tier-2 India (Amritsar, Goa examples); but 8.5% fee load heavy at Madurai ADRs; limited IHG loyalty traffic in city | E19: DOES NOT FIT — 72 keys below Taj/Vivanta minimum (100+); Ginger is budget positioning (₹2,500-3,500 ADR) which conflicts with 4-star target; IHCL unlikely to accept Madurai deal | F19: DOES NOT FIT — 72 keys below Marriott minimum (100+); Marriott would not consider this property size; Madurai is not a Bonvoy-priority market | G19: MODERATE FIT — Keys Select brand aligns with Tier-2; but ₹3,000-4,000 ADR positioning is BELOW target; would cannibalize premium 4-star positioning
B20: Track Record in Indian Tier-2 | C20: Numerous successful independents in Tier-2 (GRT Grand Madurai, Regenta Central Madurai, Hotel Sangam); local operator knowledge is competitive advantage | D20: IHG: Holiday Inn Express Amritsar, Jaipur, Nashik — mixed results; Wyndham Ramada: present in Lucknow, Udaipur — moderate success with value segment | E20: IHCL Ginger: 80+ hotels pan-India including Tier-2/3; Vivanta: limited to Tier-1 and major tourist cities; no Taj/Vivanta in Madurai currently | F20: Marriott: Fairfield by Marriott in Lucknow, Amritsar; limited Tier-2 penetration; focus remains metro/resort markets; no Marriott brand in Madurai | G20: Lemon Tree: 90+ hotels including 30+ in Tier-2/3 cities; Keys Select in Ludhiana, Thiruvananthapuram — strongest Tier-2 presence among chains
B21: Key Risk for V3 Grand Madurai | C21: OTA dependency (60-70% initially); quality consistency without brand SOPs; talent retention in Madurai labor market; building reputation from zero | D21: Fee erosion makes ₹4,000-5,000 ADR hotel marginal; PIP refresh cost every 5 years (₹0.5-1 Cr); brand may underperform vs fees in Tier-2 | E21: DISQUALIFIED on key count (72 < 100 minimum); even if accepted, fee structure would destroy 40% of operating profit; 15-20 year lock-in unacceptable | F21: DISQUALIFIED on key count (72 < 100 minimum); Marriott's fee structure is highest in industry; 20-25 year lock-in severely impairs exit flexibility | G21: ADR positioning mismatch — Lemon Tree's ₹3,000-4,000 ADR range undercuts the 4-star premium positioning; would limit revenue upside
B24: 10-YEAR FINANCIAL IMPACT BY OPERATING MODEL (₹ Crore, Phased 72-Key Basis, Base Case)
B25: ₹ Crore | C25: Yr 1 | D25: Yr 2 | E25: Yr 3 | F25: Yr 4 | G25: Yr 5 | H25: Yr 6 | I25: Yr 7 | J25: Yr 8 | K25: Yr 9 | L25: Yr 10
B26: Base Revenue (all models) | C26: 7.33 | D26: 8.73 | E26: 10.02 | F26: 12.64 | G26: 15.17 | H26: 15.93 | I26: 16.73 | J26: 17.57 | K26: 18.44 | L26: 19.37
B28: MODEL 1: INDEPENDENT (SELECTED ✓)
B29: Franchise / Mgmt Fees | C29: 0 | D29: 0 | E29: 0 | F29: 0 | G29: 0 | H29: 0 | I29: 0 | J29: 0 | K29: 0 | L29: 0
B30: EBITDA Margin | C30: 0.404 | D30: 0.404 | E30: 0.404 | F30: 0.404 | G30: 0.404 | H30: 0.404 | I30: 0.404 | J30: 0.404 | K30: 0.404 | L30: 0.404
B31: EBITDA | C31: =C26*C30 -> 2.96132 | D31: =D26*D30 -> 3.52692 | E31: =E26*E30 -> 4.04808 | F31: =F26*F30 -> 5.10656 | G31: =G26*G30 -> 6.12868 | H31: =H26*H30 -> 6.43572 | I31: =I26*I30 -> 6.75892 | J31: =J26*J30 -> 7.09828 | ... L31: =L26*L30 -> 7.82548
B33: MODEL 2: IHG FRANCHISE (Holiday Inn Express — 8.5% of room revenue)
B34: Revenue (with brand premium) | C34: =C26*1.05 -> 7.6965 | D34: =D26*1.05 -> 9.1665 | E34: =E26*1.05 -> 10.521 | F34: =F26*1.05 -> 13.272 | G34: =G26*1.05 -> 15.9285 | H34: =H26*1.05 -> 16.7265 | I34: =I26*1.05 -> 17.5665 | J34: =J26*1.05 -> 18.4485 | ... L34: =L26*1.05 -> 20.3385
B35: (-) IHG Fees (8.5% of room rev = 5.95% of total) | C35: =C34*0.0595 -> 0.45794175 | D35: =D34*0.0595 -> 0.54540675 | E35: =E34*0.0595 -> 0.6259995 | F35: =F34*0.0595 -> 0.789684 | G35: =G34*0.0595 -> 0.94774575 | H35: =H34*0.0595 -> 0.99522675 | I35: =I34*0.0595 -> 1.0452067 | J35: =J34*0.0595 -> 1.0976858 | ... L35: =L34*0.0595 -> 1.2101408
B36: (-) PIP Compliance (₹0.90 Cr amortized) | C36: 0.09 | D36: 0.09 | E36: 0.09 | F36: 0.09 | G36: 0.09 | H36: 0.09 | I36: 0.09 | J36: 0.09 | K36: 0.09 | L36: 0.09
B37: EBITDA (net of IHG fees) | C37: =C34*0.404-C35-C36 -> 2.5614443 | D37: =D34*0.404-D35-D36 -> 3.0678593 | E37: =E34*0.404-E35-E36 -> 3.5344845 | F37: =F34*0.404-F35-F36 -> 4.482204 | G37: =G34*0.404-G35-G36 -> 5.3973683 | H37: =H34*0.404-H35-H36 -> 5.6722793 | I37: =I34*0.404-I35-I36 -> 5.9616593 | J37: =J34*0.404-J35-J36 -> 6.2655083 | ... L37: =L34*0.404-L35-L36 -> 6.9166133
B38: Effective EBITDA Margin | C38: =C37/C34 -> 0.33280637 | D38: =D37/D34 -> 0.33468164 | E38: =E37/E34 -> 0.33594568 | F38: =F37/F34 -> 0.33771881 | G38: =G37/G34 -> 0.33884975 | H38: =H37/H34 -> 0.33911932 | I38: =I37/I34 -> 0.33937661 | J38: =J37/J34 -> 0.33962155 | ... L38: =L37/L34 -> 0.34007489
B40: MODEL 3: IHCL TAJ / VIVANTA (Mgmt Contract) — ⚠ DISQUALIFIED: 72 keys < 100 min
B41: Revenue (with brand premium) | C41: =C26*1.1 -> 8.063 | D41: =D26*1.1 -> 9.603 | E41: =E26*1.1 -> 11.022 | F41: =F26*1.1 -> 13.904 | G41: =G26*1.1 -> 16.687 | H41: =H26*1.1 -> 17.523 | I41: =I26*1.1 -> 18.403 | J41: =J26*1.1 -> 19.327 | ... L41: =L26*1.1 -> 21.307
B42: (-) IHCL Base Fee (2.5% of revenue) | C42: =C41*0.025 -> 0.201575 | D42: =D41*0.025 -> 0.240075 | E42: =E41*0.025 -> 0.27555 | F42: =F41*0.025 -> 0.3476 | G42: =G41*0.025 -> 0.417175 | H42: =H41*0.025 -> 0.438075 | I42: =I41*0.025 -> 0.460075 | J42: =J41*0.025 -> 0.483175 | ... L42: =L41*0.025 -> 0.532675
B43: (-) Incentive Fee (8% of GOP) | C43: =C41*0.404*0.1 -> 0.3257452 | D43: =D41*0.404*0.1 -> 0.3879612 | E43: =E41*0.404*0.1 -> 0.4452888 | F43: =F41*0.404*0.1 -> 0.5617216 | G43: =G41*0.404*0.1 -> 0.6741548 | H43: =H41*0.404*0.1 -> 0.7079292 | I43: =I41*0.404*0.1 -> 0.7434812 | J43: =J41*0.404*0.1 -> 0.7808108 | ... L43: =L41*0.404*0.1 -> 0.8608028
B44: (-) Tech Services + Marketing (3.5% of revenue) | C44: =C41*0.03 -> 0.24189 | D44: =D41*0.03 -> 0.28809 | E44: =E41*0.03 -> 0.33066 | F44: =F41*0.03 -> 0.41712 | G44: =G41*0.03 -> 0.50061 | H44: =H41*0.03 -> 0.52569 | I44: =I41*0.03 -> 0.55209 | J44: =J41*0.03 -> 0.57981 | ... L44: =L41*0.03 -> 0.63921
B45: (-) Brand Standard CAPEX (₹2.0 Cr amortized) | C45: 0.2 | D45: 0.2 | E45: 0.2 | F45: 0.2 | G45: 0.2 | H45: 0.2 | I45: 0.2 | J45: 0.2 | K45: 0.2 | L45: 0.2
B46: (-) GM Cost (no owner-operator saving — ₹30L/yr) | C46: 0.3 | D46: 0.3 | E46: 0.3 | F46: 0.3 | G46: 0.3 | H46: 0.3 | I46: 0.3 | J46: 0.3 | K46: 0.3 | L46: 0.3
B47: EBITDA (net of IHCL fees) | C47: =C41*0.404-C42-C43-C44-C45-C46 -> 1.9882418 | D47: =D41*0.404-D42-D43-D44-D45-D46 -> 2.4634858 | E47: =E41*0.404-E42-E43-E44-E45-E46 -> 2.9013892 | F47: =F41*0.404-F42-F43-F44-F45-F46 -> 3.7907744 | G47: =G41*0.404-G42-G43-G44-G45-G46 -> 4.6496082 | H47: =H41*0.404-H42-H43-H44-H45-H46 -> 4.9075978 | I47: =I41*0.404-I42-I43-I44-I45-I46 -> 5.1791658 | J47: =J41*0.404-J42-J43-J44-J45-J46 -> 5.4643122 | ... L47: =L41*0.404-L42-L43-L44-L45-L46 -> 6.0753402
B48: Effective EBITDA Margin | C48: =C47/C41 -> 0.24658834 | D48: =D47/D41 -> 0.25653294 | E48: =E47/E41 -> 0.26323618 | F48: =F47/F41 -> 0.27263913 | G48: =G47/G41 -> 0.27863656 | H48: =H47/H41 -> 0.28006607 | I48: =I47/I41 -> 0.28143052 | J48: =J47/J41 -> 0.28272946 | ... L48: =L47/L41 -> 0.28513353
B50: MODEL 4: MARRIOTT / HYATT (Mgmt Contract) — ⚠ DISQUALIFIED: 72 keys < 100 min
B51: Revenue (with Bonvoy premium +8%) | C51: =C26*1.08 -> 7.9164 | D51: =D26*1.08 -> 9.4284 | E51: =E26*1.08 -> 10.8216 | F51: =F26*1.08 -> 13.6512 | G51: =G26*1.08 -> 16.3836 | H51: =H26*1.08 -> 17.2044 | I51: =I26*1.08 -> 18.0684 | J51: =J26*1.08 -> 18.9756 | ... L51: =L26*1.08 -> 20.9196
B52: (-) Marriott Base Fee (3% of total revenue) | C52: =C51*0.03 -> 0.237492 | D52: =D51*0.03 -> 0.282852 | E52: =E51*0.03 -> 0.324648 | F52: =F51*0.03 -> 0.409536 | G52: =G51*0.03 -> 0.491508 | H52: =H51*0.03 -> 0.516132 | I52: =I51*0.03 -> 0.542052 | J52: =J51*0.03 -> 0.569268 | ... L52: =L51*0.03 -> 0.627588
B53: (-) Incentive Fee (10% of GOP) | C53: =C51*0.404*0.1 -> 0.31982256 | D53: =D51*0.404*0.1 -> 0.38090736 | E53: =E51*0.404*0.1 -> 0.43719264 | F53: =F51*0.404*0.1 -> 0.55150848 | G53: =G51*0.404*0.1 -> 0.66189744 | H53: =H51*0.404*0.1 -> 0.69505776 | I53: =I51*0.404*0.1 -> 0.72996336 | J53: =J51*0.404*0.1 -> 0.76661424 | ... L53: =L51*0.404*0.1 -> 0.84515184
B54: (-) System/Loyalty + Mktg (7% of room rev) | C54: =C51*0.7*0.07 -> 0.3879036 | D54: =D51*0.7*0.07 -> 0.4619916 | E54: =E51*0.7*0.07 -> 0.5302584 | F54: =F51*0.7*0.07 -> 0.6689088 | G54: =G51*0.7*0.07 -> 0.8027964 | H54: =H51*0.7*0.07 -> 0.8430156 | I54: =I51*0.7*0.07 -> 0.8853516 | J54: =J51*0.7*0.07 -> 0.9298044 | ... L54: =L51*0.7*0.07 -> 1.0250604
B55: (-) Brand CAPEX (₹2.75 Cr amortized) + GM Cost | C55: 0.575 | D55: 0.575 | E55: 0.575 | F55: 0.575 | G55: 0.575 | H55: 0.575 | I55: 0.575 | J55: 0.575 | K55: 0.575 | L55: 0.575
B56: EBITDA (net of Marriott fees) | C56: =C51*0.404-C52-C53-C54-C55 -> 1.6780074 | D56: =D51*0.404-D52-D53-D54-D55 -> 2.1083226 | E56: =E51*0.404-E52-E53-E54-E55 -> 2.5048274 | F56: =F51*0.404-F52-F53-F54-F55 -> 3.3101315 | G56: =G51*0.404-G52-G53-G54-G55 -> 4.0877726 | H56: =H51*0.404-H52-H53-H54-H55 -> 4.3213722 | I56: =I51*0.404-I52-I53-I54-I55 -> 4.5672666 | J56: =J51*0.404-J52-J53-J54-J55 -> 4.8254558 | ... L56: =L51*0.404-L52-L53-L54-L55 -> 5.3787182
B57: Effective EBITDA Margin | C57: =C56/C51 -> 0.21196597 | D57: =D56/D51 -> 0.22361404 | E57: =E56/E51 -> 0.23146553 | F57: =F56/F51 -> 0.24247916 | G57: =G56/G51 -> 0.24950393 | H57: =H56/H51 -> 0.25117832 | I57: =I56/I51 -> 0.25277648 | J57: =J56/J51 -> 0.25429793 | ... L57: =L56/L51 -> 0.25711381
B59: MODEL 5: LEMON TREE / KEYS SELECT (Franchise-Lite — 4.5% of total revenue)
B60: Revenue (REDUCED — Lemon Tree ADR ₹3,000-4,000 = -10%) | C60: =C26*0.9 -> 6.597 | D60: =D26*0.9 -> 7.857 | E60: =E26*0.9 -> 9.018 | F60: =F26*0.9 -> 11.376 | G60: =G26*0.9 -> 13.653 | H60: =H26*0.9 -> 14.337 | I60: =I26*0.9 -> 15.057 | J60: =J26*0.9 -> 15.813 | ... L60: =L26*0.9 -> 17.433
B61: (-) Lemon Tree Fees (4.5% of total revenue) | C61: =C60*0.045 -> 0.296865 | D61: =D60*0.045 -> 0.353565 | E61: =E60*0.045 -> 0.40581 | F61: =F60*0.045 -> 0.51192 | G61: =G60*0.045 -> 0.614385 | H61: =H60*0.045 -> 0.645165 | I61: =I60*0.045 -> 0.677565 | J61: =J60*0.045 -> 0.711585 | ... L61: =L60*0.045 -> 0.784485
B62: (-) PIP Compliance (₹0.45 Cr amortized) | C62: 0.045 | D62: 0.045 | E62: 0.045 | F62: 0.045 | G62: 0.045 | H62: 0.045 | I62: 0.045 | J62: 0.045 | K62: 0.045 | L62: 0.045
B63: EBITDA (net of Lemon Tree fees) | C63: =C60*0.404-C61-C62 -> 2.323323 | D63: =D60*0.404-D61-D62 -> 2.775663 | E63: =E60*0.404-E61-E62 -> 3.192462 | F63: =F60*0.404-F61-F62 -> 4.038984 | G63: =G60*0.404-G61-G62 -> 4.856427 | H63: =H60*0.404-H61-H62 -> 5.101983 | I63: =I60*0.404-I61-I62 -> 5.360463 | J63: =J60*0.404-J61-J62 -> 5.631867 | ... L63: =L60*0.404-L61-L62 -> 6.213447
B64: Effective EBITDA Margin | C64: =C63/C60 -> 0.35217872 | D64: =D63/D60 -> 0.35327262 | E64: =E63/E60 -> 0.35400998 | F64: =F63/F60 -> 0.3550443 | G64: =G63/G60 -> 0.35570402 | H64: =H63/H60 -> 0.35586127 | I64: =I63/I60 -> 0.35601136 | J64: =J63/J60 -> 0.35615424 | ... L64: =L63/L60 -> 0.35641869
B70: Metric | C70: 1. Independent ✓ | D70: 2. IHG Franchise | E70: 3. IHCL Taj (DISQ.) | F70: 4. Marriott (DISQ.) | G70: 5. Lemon Tree | H70: Board Hurdle
B71: 10-Year Cumulative EBITDA (₹ Cr) | C71: =SUM(C31:L31) -> 57.33972 | D71: =SUM(C37:L37) -> 50.439629 | E71: =SUM(C47:L47) -> 43.179558 | F71: =SUM(C54:L54) -> 7.5109356 | G71: =SUM(C63:L63) -> 45.407583
B72: 10-Year Fee Leakage (₹ Cr) | C72: 0 | D72: =SUM(C35:L35)+SUM(C36:L36) -> 9.7670768 | E72: =SUM(C42:L42)+SUM(C43:L43)+SUM(C44:L44)+SUM(C45:L45)+SUM(C46:L46) -> 19.894134 | F72: =SUM(C52:L52)+SUM(C53:L53)+SUM(C54:L54)+SUM(C55:L55) -> 24.052157 | G72: =SUM(C61:L61)+SUM(C62:L62) -> 6.198165
B73: Year 10 EBITDA (₹ Cr) | C73: =L31 -> 7.82548 | D73: =L37 -> 6.9166133 | E73: =L47 -> 6.0753402 | F73: =L56 -> 5.3787182 | G73: =L63 -> 6.213447
B74: Exit Value @ 12x (₹ Cr) | C74: =C73*12 -> 93.90576 | D74: =D73*12 -> 82.999359 | E74: =E73*12 -> 72.904082 | F74: =F73*12 -> 64.544618 | G74: =G73*12 -> 74.561364
B75: Total Investment (₹ Cr) | C75: 43 | D75: 43.9 | E75: 45 | F75: 45.75 | G75: 43.45
B77: 10-YEAR IRR | C77: =IRR(P5:Z5) -> 0.15732336 | D77: =IRR(P6:Z6) -> 0.13395131 | E77: =IRR(P7:Z7) -> 0.10816813 | F77: =IRR(P8:Z8) -> 0.087534694 | G77: =IRR(P9:Z9) -> 0.1190784 | H77: 0.12
B78: NPV @ 12% (₹ Cr) | C78: =NPV(0.12,Q5:Z5)+P5 -> 12.54369 | D78: =NPV(0.12,Q6:Z6)+P6 -> 4.5418407 | E78: =NPV(0.12,Q7:Z7)+P7 -> -3.7482321 | F78: =NPV(0.12,Q8:Z8)+P8 -> -9.9529631 | G78: =NPV(0.12,Q9:Z9)+P9 -> -0.28639046 | H78: >₹0
B79: Return Multiple | C79: =SUM(Q5:Z5)/(-P5) -> 3.3475693 | D79: =SUM(Q6:Z6)/(-P6) -> 2.8733255 | E79: =SUM(Q7:Z7)/(-P7) -> 2.4174142 | F79: =SUM(Q8:Z8)/(-P8) -> 2.0791117 | G79: =SUM(Q9:Z9)/(-P9) -> 2.5930713 | H79: >2.0x
B80: IRR Drag from Fees (vs Independent) | C80: — | D80: =D77-C77 -> -0.023372054 | E80: =E77-C77 -> -0.04915523 | F80: =F77-C77 -> -0.069788669 | G80: =G77-C77 -> -0.038244958
B81: Passes 12% Board Hurdle? | C81: =IF(C77>=0.12,"✓ YES","✗ NO") -> ✓ YES | D81: =IF(D77>=0.12,"✓ YES","✗ NO") -> ✓ YES | E81: =IF(E77>=0.12,"✓ YES","✗ NO") -> ✗ NO | F81: =IF(F77>=0.12,"✓ YES","✗ NO") -> ✗ NO | G81: =IF(G77>=0.12,"✓ YES","✗ NO") -> ✗ NO
B82: Passes 12% Hurdle? | C82: =IF(C77>0.12,"✓ YES","✗ NO") -> ✓ YES | D82: =IF(D77>0.12,"✓ YES","✗ NO") -> ✓ YES | E82: =IF(E77>0.12,"✓ YES","✗ NO") -> ✗ NO | F82: =IF(F77>0.12,"✓ YES","✗ NO") -> ✗ NO
B83: STRATEGIC ASSESSMENT — BRAND-SPECIFIC ANALYSIS
B84: Factor | C84: 1. Independent ✓ | D84: 2. IHG Franchise | E84: 3. IHCL Taj/Vivanta | F84: 4. Marriott/Hyatt | G84: 5. Lemon Tree/Keys
B85: STRENGTHS
B86: Cost Efficiency | C86: BEST: 40.4% EBITDA margin; ₹0 fee leakage over 10 years; owner-operator saves ₹30L/yr vs hired GM; full procurement control | D86: 33-36% EBITDA after 8.5% room revenue fee; ₹0.9 Cr PIP upfront; IHG procurement mandates may increase costs 5-10% | E86: 27-33% EBITDA after base+incentive+tech fees; ₹2 Cr brand CAPEX; hired GM costs ₹30-50L/yr; Taj mandates imported finishes | F86: WORST: 21-26% EBITDA; 3% base + 10% incentive + 7% system fees stack to ~20% of revenue; ₹2.75 Cr brand CAPEX; Marriott-mandated vendors | G86: 36-38% EBITDA; lightest fee structure (4.5%); ₹0.45 Cr PIP; Indian supply chain keeps costs low; BUT ADR reduction offsets savings
B87: Distribution & Demand | C87: Must build direct: MakeMyTrip, Booking.com, Google Hotels; offset by 160-212 MOU room-nights/month from medical+corporate anchors | D87: IHG Rewards (100M members) + GDS access; Holiday Inn Express well-known in India; BUT limited IHG loyalty traffic in Madurai specifically | E87: Taj InnerCircle (3.5M members); strongest domestic corporate loyalty; IHCL government/PSU preferred vendor lists; strong for medical tourism premium | F87: Marriott Bonvoy (200M members, 8M India); DOMINANT on global corporate RFP mandates; strongest distribution globally; BUT Madurai is not Bonvoy-priority market | G87: Lemon Tree Smiles (1M+ members); growing domestic base; strong OTA presence in Tier-2; BUT limited international reach; lower brand cachet
B88: Madurai Market Fit | C88: STRONGEST: No 4-star competitor; owner knows local medical/corporate/temple demand; ₹4,000-5,000 ADR sweet spot; anchor MOUs replace brand distribution | D88: MODERATE: Holiday Inn Express format works in Tier-2 (Amritsar, Nashik precedents); BUT 8.5% fees heavy at Madurai ADRs; limited IHG loyalty presence | E88: DOES NOT FIT: 72 keys < 100 key minimum; Vivanta only in Tier-1/resort; Ginger is budget brand (₹2,500-3,500 ADR) — conflicts with 4-star positioning | F88: DOES NOT FIT: 72 keys < 100 key minimum for Fairfield/Courtyard/Hyatt Place; Marriott has no existing Madurai presence; Bonvoy traffic negligible in city | G88: MODERATE: Keys Select works in Tier-2 (Ludhiana, Thiruvananthapuram); BUT positions at ₹3,000-4,000 ADR — BELOW target; would cannibalize 4-star premium
B89: WEAKNESSES
B90: Key Vulnerabilities | C90: OTA dependency 60-70% initially; no brand quality framework; talent harder to attract without brand name; reputation must be built from zero | D90: Fee erosion on already-thin Tier-2 margins; PIP refresh ₹0.5-1 Cr every 5 years; IHG may mandate room renovation cycles; limited flexibility on F&B | E90: DISQUALIFIED: 72 keys below 100-key minimum; even hypothetically — IHCL fees absorb 30-40% of GOP; 15-20 year lock-in; brand controls pricing/staffing/procurement | F90: DISQUALIFIED: 72 keys below 100-key minimum; highest fee burden in industry (~20% of revenue); 20-25 year lock-in; exit penalty up to ₹9-11 Cr; loss of all operational control | G90: ADR REDUCTION: Lemon Tree brand positions property at ₹3,000-4,000 — permanently caps revenue upside; 8-10 year lock-in; may conflict with premium medical tourism positioning
B91: Exit & Flexibility | C91: BEST: No contractual lock-in; can sell property freely; can add brand later at Year 3-5 if needed; full optionality preserved | D91: 10-15 year term; exit penalty 3-5 years of fees (₹3-6 Cr); PIP compliance transfers to buyer; franchise can be terminated but brand infrastructure wasted | E91: 15-20 year term; 24-month notice + 2-3 years liquidated damages; change of ownership requires IHCL consent; severely limits exit flexibility | F91: 20-25 year term (LONGEST); exit penalty up to 5 years projected fees (₹9-11 Cr); performance test only after Year 5 with narrow cure; property effectively locked | G91: 8-10 year term (SHORTEST); 12-month notice; moderate exit flexibility; renewal at mutual option; BUT ADR reputation damage persists after de-branding
B93: INVESTMENT COMMITTEE RECOMMENDATION
M94: =L31+C74 -> 101.73124
B95: VERDICT: INDEPENDENT OWNER-OPERATED MODEL (Model 1) IS THE OPTIMAL CHOICE | M95: =L37+D74 -> 89.915972
M96: =L47+E74 -> 78.979423
B97: 1. ELIMINATORY CRITERION — Minimum Key Count | C97: Marriott (Fairfield/Courtyard) and IHCL (Taj/Vivanta) BOTH require minimum 100 keys for Tier-2 India. V3 Grand Madurai at 72 keys is categorically ineligible. This is not a negotiable threshold — it is embedded in brand standards. These two options are ELIMINATED from consideration regardless of financial analysis. | M97: =L54+F74 -> 65.569678
B99: 2. FINANCIAL SUPERIORITY — Highest IRR by 220+ bps | C99: Independent model delivers 15.7% IRR vs IHG Franchise at 13.4% — a 230 bps gap. Over 10 years, fee leakage under IHG totals ₹9.8 Cr (equivalent to 23% of total investment). The ₹0 fee structure of independent operation directly flows to owner EBITDA, producing ₹57.3 Cr cumulative EBITDA vs ₹50.4 Cr under IHG.
B101: 3. LEMON TREE ADR TRAP — Brand Reduces Revenue | C101: While Lemon Tree/Keys Select qualifies on key count (50+ minimum) and has the lowest fee burden (4.5%), it positions the property at ₹3,000-4,000 ADR — 10-15% BELOW V3's target of ₹4,000-5,000. This ADR reduction destroys more value than the fees save. Lemon Tree IRR of 11.9% FAILS the 12% board hurdle. Branding with Lemon Tree would permanently cap the property's revenue ceiling.
B103: 4. ANCHOR PARTNERSHIPS REPLACE BRAND DISTRIBUTION | C103: The medical corridor MOUs (Vikram Hospital 40-50 room-nights/month, Hannah Joseph Hospital 20-25, Aravind Eye Hospital 10-15) plus corporate partnerships (TCS, Infosys, HCL, Cognizant) deliver 160-212 guaranteed room-nights/month — equivalent to 8-11% baseline occupancy. This anchored demand pipeline replicates the distribution advantage that brands provide, without the associated fee burden.
B105: 5. MADURAI MARKET DYNAMICS FAVOR INDEPENDENCE | C105: Madurai's 4-star hotel market has no direct branded competitor in the ₹4,000-5,000 ADR segment. The demand drivers are predominantly domestic (medical tourism 28%, corporate 35%, temple pilgrimage 22%) — segments where global brand loyalty programs add minimal incremental value. An independent operator with local market knowledge and established corporate relationships has a structural advantage.
B107: 6. OPTIONALITY PRESERVED — CAN ADD BRAND LATER | C107: The independent model preserves full strategic optionality. If market conditions change (new competitor, OTA costs exceed 20%, international medical tourism exceeds 30% of mix), the property can pursue franchise affiliation at Year 3-5 with no contractual barriers. Starting branded locks in 10-25 year commitments; starting independent keeps all options open.
B109: 7. OWNER-OPERATOR ADVANTAGE — ₹30L/yr SAVINGS | C109: Second-generation hotelier with established industry relationships eliminates the ₹30-50L/year GM hire cost that branded models require. This is not merely a cost saving — it ensures aligned incentives between property performance and owner returns, a structural advantage that management contracts specifically lack.
B110: BRAND ADOPTION TRIGGERS — When to Reconsider Operating Model
B111: 8. RISK MITIGATION WITHOUT BRAND COST | C111: Key independent model risks (OTA dependency, quality consistency, talent retention) are mitigated through: (a) Anchor MOUs reducing OTA dependency to <50% by Year 2, (b) Owner's established hospitality SOPs from family business, (c) Madurai labor market offering competitive cost advantage vs metro cities, (d) Phase 2 decision gate at Month 36 provides natural checkpoint.
B112: OTA commissions exceed 20% blended | C112: >20% blended | D112: Evaluate franchise for GDS/loyalty savings | E112: Year 3+
B113: Occupancy plateaus below 65% after Year 3 | C113: <65% trailing 12-month | D113: Franchise brand may lift occupancy 5-8% | E113: Year 3
B114: BRAND ADOPTION TRIGGERS — CONDITIONS FOR FUTURE RECONSIDERATION | C114: >30% international guests | D114: IHG/Wyndham for global distribution | E114: Year 4+
B115: Trigger Condition | C115: Threshold | D115: Recommended Action | E115: Timing | F115: Preferred Brand
B116: OTA commission burden exceeds 20% blended rate | C116: >20% blended OTA commission | D116: Evaluate IHG franchise for GDS/loyalty distribution savings | E116: Year 3+ | F116: IHG Holiday Inn Express
B117: Occupancy plateaus below 65% after 36 months | C117: <65% trailing 12-month average by Month 36 | D117: Franchise brand may lift occupancy 3-5 percentage points | E117: Year 3 | F117: IHG or Wyndham Ramada
B118: International medical tourism exceeds 30% of guest mix | C118: >30% international guests (non-Indian passport) | D118: Global distribution becomes valuable; IHG for international reach | E118: Year 4+ | F118: IHG or Wyndham
B119: New branded 4-star hotel opens within 5km radius | C119: Direct 4-star competitor with global brand affiliation | D119: Franchise branding to achieve parity; competitive response | E119: As needed | F119: IHG Holiday Inn Express
B120: Phase 2 expansion triggers 100+ key threshold | C120: Phase 2 completed AND further expansion to 100+ keys planned | D120: At 100+ keys, IHCL Vivanta or Marriott Fairfield become viable options | E120: Year 7+ | F120: IHCL Vivanta or Marriott Fairfield
B121: OTA guest ratings fall below 4.0 across platforms | C121: <4.0 rating on Booking.com, MakeMyTrip, Google for 6+ months | D121: Brand framework may enforce quality consistency through SOPs | E121: Year 2+ | F121: Lemon Tree (lightest intervention)
...

Sheet 13. Phase 2 Gate
B1: Phase 2 Investment Gate Criteria
B2: V3 Grand Madurai • Confidential Board Material • February 2026
B4: PHASE 2 DECISION GATE
B5: 8-Point Checklist at Month 36 · Go/No-Go Framework
B7: DECISION FRAMEWORK
B8: Outcome | C8: Criteria Met | D8: Action | E8: Investment
B9: ✅ PROCEED | C9: 8 of 8 | D9: Execute Phase 2 expansion | E9: ₹7.3 Crore
B10: ⏸ DELAY | C10: 6-7 of 8 | D10: Delay 6-12 months, reassess | E10: Hold
B11: ❌ OPTIMIZE | C11: <6 of 8 | D11: Optimize Phase 1, stay at 55 keys | E11: ₹0
B13: 8-POINT ASSESSMENT CHECKLIST
B14: # | C14: Criterion | D14: Threshold | E14: Assessment Period | F14: Status | G14: Notes
B15: 1 | C15: Phase 1 Occupancy | D15: ≥ 70% | E15: Trailing 6-month average | F15: TBD | G15: Core operating metric
B16: 2 | C16: Phase 1 ADR | D16: ≥ ₹4,800 | E16: Trailing 6-month average | F16: TBD | G16: Pricing power indicator
B17: 3 | C17: Phase 1 EBITDA Margin | D17: ≥ 38% | E17: Trailing 12-month average | F17: TBD | G17: Operating efficiency
B18: 4 | C18: OTA Ratings | D18: ≥ 4.2 / 5.0 | E18: TripAdvisor, Google, Booking.com | F18: TBD | G18: Guest satisfaction
B19: 5 | C19: Hannah Joseph MOU | D19: ≥ 20 room-nights/month | E19: Trailing 3-month average | F19: TBD | G19: Anchor validation
B20: 6 | C20: Corporate Contracts | D20: ≥ 8 active accounts | E20: Monthly recurring bookings | F20: TBD | G20: Revenue diversification
B21: 7 | C21: Competitive Landscape | D21: No new 4-star within 5km | E21: Market survey | F21: TBD | G21: Supply-side risk
B22: 8 | C22: Macro Environment | D22: Stable/positive | E22: Temple tourism, airport ops | F22: TBD | G22: External factors
B24: Criteria Met | C24: — / 8
B25: Decision | C25: Pending Month 36 Assessment
B27: GO / NO-GO COMPARISON
B28: Metric | C28: Stay at 55 Keys | D28: Expand to 72 Keys | E28: Delta
B29: Total Investment | C29: ₹35.7 Cr | D29: ₹43.0 Cr | E29: +₹7.3 Cr
B30: Year 10 Revenue | C30: ₹14.79 Cr | D30: ₹19.37 Cr | E30: +₹4.58 Cr
B31: Year 10 EBITDA | C31: ₹5.98 Cr | D31: ₹7.83 Cr | E31: +₹1.85 Cr
B32: 10-Year IRR | C32: 0.176 | D32: 0.178 | E32: 0.002
B33: NPV @ 12% | C33: ₹13.4 Cr | D33: ₹15.9 Cr | E33: +₹2.5 Cr
B34: Return Multiple | C34: 2.79x | D34: 2.71x | E34: -0.08x
B35: Exit Value (12x) | C35: ₹71.8 Cr | D35: ₹93.9 Cr | E35: +₹22.1 Cr
B36: Payback Period | C36: 7.6 years | D36: 7.8 years | E36: +0.2 years
B37: Risk Profile | C37: Lower (proven) | D37: Moderate (execution)
B39: PHASE 2 INCREMENTAL RETURNS
B40: Phase 2 Investment | C40: ₹7.3 Cr
B41: Phase 2 Incremental Annual EBITDA (stabilized) | C41: ₹1.85 Cr
B42: Phase 2 Standalone IRR | C42: ~22% | D42: Attractive on standalone basis
B43: Phase 2 Payback | C43: ~4.5 years | D43: On incremental investment
B44: Recommendation | C44: PROCEED if gates met | D44: Higher IRR on marginal capital
B46: © 2025 Giritharan Chockalingam. All Rights Reserved. | This financial model and all associated intellectual property are proprietary and confidential.
B47: CONFIDENTIAL — For Board Approval Use Only | V3 Grand Madurai Investment Model v1.0 | Unauthorized reproduction or distribution is strictly prohibited.

Sheet 15. WACC Calculation
B1: WACC & Cost of Capital Analysis
B2: V3 Grand Madurai • Comparable Company Method • February 2026
B5: RISK-FREE RATE
B6: India 10-Year G-Sec Yield (Feb 2026) | C6: 0.0667 | D6: Source: Trading Economics, RBI
B7: Risk-Free Rate Used | C7: {=C6} -> 0.0667
B10: COMPARABLE INDIAN HOSPITALITY COMPANIES
B11: Company | C11: Ticker | D11: Mkt Cap | E11: Levered β | F11: D/E Ratio | G11: Unlevered β | H11: Notes
B12: Indian Hotels Company Ltd (IHCL) | C12: INDHOTEL.NS | D12: Large Cap | E12: 1.4 | F12: 0.35 | G12: =E12/(1+(1-0.25)*F12) -> 1.1089109 | H12: 3-year beta, premium luxury
B13: Lemon Tree Hotels Ltd | C13: LEMONTREE.NS | D13: Mid Cap | E13: -0.44 | F13: 0.45 | G13: 0.85 | H13: Mid-market, beta anomaly adjusted
B14: EIH Limited (Oberoi) | C14: EIHOTEL.NS | D14: Large Cap | E14: 1.02 | F14: 0.25 | G14: =E14/(1+(1-0.25)*F14) -> 0.85894737 | H14: Ultra-luxury, conservative leverage
B16: Average Unlevered Beta (Comparables) | G16: =AVERAGE(G12:G14) -> 0.93928609 | H16: Arithmetic mean of unlevered betas
B19: RISK PREMIUM BUILD-UP
B20: Base Equity Risk Premium (India) | C20: 0.075 | D20: NYU Damodaran India ERP, Jan 2025
B21: Country Risk Premium (India BBB- rating) | C21: 0.02 | D21: Emerging market sovereign spread
B22: Size Premium (Boutique Hotel) | C22: 0.03 | D22: Sub-₹100 Cr asset, illiquid
B23: Project-Specific Risk Premium | C23: 0.015 | D23: New hotel, unproven market, execution risk
B25: Total Equity Risk Premium | C25: =SUM(C20:C23) -> 0.14
B28: V3 GRAND MADURAI BETA ADJUSTMENT
B29: Average Unlevered Beta (from comparables) | C29: {=G16} -> 0.93928609
B30: V3 Grand Target D/E Ratio | C30: 0.67 | D30: 40% debt / 60% equity
B31: Tax Rate (India Corporate) | C31: 0.25 | D31: Applicable corporate tax
B33: V3 Grand Levered Beta | C33: =C29*(1+(1-C31)*C30) -> 1.4112773
B34: Beta re-levered to V3 Grand capital structure
B37: WEIGHTED AVERAGE COST OF CAPITAL (WACC)
B38: Risk-Free Rate | C38: {=C7} -> 0.0667
B39: V3 Grand Levered Beta | C39: {=C33} -> 1.4112773
B40: Total Equity Risk Premium | C40: {=C25} -> 0.14
B42: Cost of Equity (CAPM) | C42: =C38+C39*C40 -> 0.26427883 | D42: Rf + β × ERP
B44: Debt Interest Rate | C44: 0.085 | D44: Bank term loan rate
B45: Tax Shield Benefit | C45: {=C31} -> 0.25
B47: After-Tax Cost of Debt | C47: =C44*(1-C45) -> 0.06375
B49: Equity Weight | C49: 0.6
B50: Debt Weight | C50: 0.4
B52: WACC (Weighted Average Cost of Capital) | C52: =(C42*C49)+(C47*C50) -> 0.1840673
B53: Reflects boutique hotel risk profile in Tier-II Indian market
B56: MODEL HURDLE RATE ASSESSMENT
B57: Current Model Hurdle Rate | C57: 0.12 | D57: Original assumption
B58: Calculated WACC (Proper Method) | C58: {=C52} -> 0.1840673
B59: Gap (Under-estimation) | C59: =C58-C57 -> 0.064067297
B61: Recommended Hurdle Rate Range | C61: 16.0% - 18.5%
B62: Conservative: 16.0% (adjust for anchor MOUs reducing risk)
B63: Base Case: 17.5% (balanced risk adjustment)
B64: Conservative WACC: 18.4% (full boutique hotel risk)
B67: WACC SENSITIVITY ANALYSIS
B68: Beta \ ERP → | C68: 0.12 | D68: 0.13 | E68: 0.14 | F68: 0.15 | H68: Rf= | I68: {=C7} -> 0.0667
B69: 1.2 | C69: =($I$68+$B69*C$68)*$I$69+$I$70*$I$71 -> 0.15192 | D69: =($I$68+$B69*D$68)*$I$69+$I$70*$I$71 -> 0.15912 | E69: =($I$68+$B69*E$68)*$I$69+$I$70*$I$71 -> 0.16632 | F69: =($I$68+$B69*F$68)*$I$69+$I$70*$I$71 -> 0.17352 | H69: Ke Weight= | I69: {=C49} -> 0.6
B70: 1.3 | C70: =($I$68+$B70*C$68)*$I$69+$I$70*$I$71 -> 0.15912 | D70: =($I$68+$B70*D$68)*$I$69+$I$70*$I$71 -> 0.16692 | E70: =($I$68+$B70*E$68)*$I$69+$I$70*$I$71 -> 0.17472 | F70: =($I$68+$B70*F$68)*$I$69+$I$70*$I$71 -> 0.18252 | H70: Kd AT= | I70: {=C47} -> 0.06375
B71: 1.41 | C71: =($I$68+$B71*C$68)*$I$69+$I$70*$I$71 -> 0.16704 | D71: =($I$68+$B71*D$68)*$I$69+$I$70*$I$71 -> 0.1755 | E71: =($I$68+$B71*E$68)*$I$69+$I$70*$I$71 -> 0.18396 | F71: =($I$68+$B71*F$68)*$I$69+$I$70*$I$71 -> 0.19242 | H71: Kd Weight= | I71: {=C50} -> 0.4
B72: 1.5 | C72: =($I$68+$B72*C$68)*$I$69+$I$70*$I$71 -> 0.17352 | D72: =($I$68+$B72*D$68)*$I$69+$I$70*$I$71 -> 0.18252 | E72: =($I$68+$B72*E$68)*$I$69+$I$70*$I$71 -> 0.19152 | F72: =($I$68+$B72*F$68)*$I$69+$I$70*$I$71 -> 0.20052
B75: DATA SOURCES:
B76: • Risk-Free Rate: India 10Y G-Sec, Trading Economics/RBI (Feb 2026)
B77: • Company Betas: Yahoo Finance, Bajaj Finserv (3-year weekly returns)
B78: • Equity Risk Premium: NYU Damodaran India ERP (Jan 2025)
B79: • D/E Ratios: Estimated based on industry averages

Sheet _ChartData
B1: Yr 1 | C1: Yr 2 | D1: Yr 3 | E1: Yr 4 | F1: Yr 5 | G1: Yr 6 | H1: Yr 7 | I1: Yr 8 | J1: Yr 9 | K1: Yr 10
A2: Revenue (₹ Cr) | B2: 7.33 | C2: 8.73 | D2: 10.02 | E2: 12.64 | F2: 15.17 | G2: 15.93 | H2: 16.73 | I2: 17.57 | J2: 18.44 | K2: 19.37
A3: EBITDA (₹ Cr) | B3: 2.93 | C3: 3.53 | D3: 4.05 | E3: 5.11 | F3: 6.07 | G3: 6.44 | H3: 6.88 | I3: 7.22 | J3: 7.68 | K3: 8.21
A5: Scenario | B5: 10-Year IRR
A6: Bear (20%) | B6: 0.143
A7: Base (60%) | B7: 0.178
A8: Bull (20%) | B8: 0.229
A10: Operating Model | B10: 10-Year IRR | C10: 12% Hurdle
A11: Independent ✓ | B11: 0.157 | C11: 0.12
A12: IHG Franchise | B12: 0.134 | C12: 0.12
A13: Lemon Tree | B13: 0.119 | C13: 0.12
A14: IHCL Taj ⚠ | B14: 0.108 | C14: 0.12
A15: Marriott ⚠ | B15: 0.088 | C15: 0.12

Sheet 14. Capital Structure Analysis
B1: V3 GRAND MADURAI | Capital Structure Analysis | Debt Scenario Comparison
B2: Prepared: February 2026 | Confidential - Board Use Only
B5: CAPITAL STRUCTURE SCENARIOS - PHASED EXPANSION (72 KEYS)
B6: ⚠️ HURDLE RATE CORRECTION IMPACT
B8: Previous model used 12% discount rate (understated WACC)
B9: Proper WACC calculation yields 17.5% hurdle (see Sheet 15: WACC Calculation)
B11: NPV Impact Comparison:
B12: • 40% Debt: Dropped from ₹18.3 Cr to ₹0.69 Cr (-96.2%) — NOW MARGINAL
B13: • 30% Debt: Dropped from ₹17.9 Cr to ₹4.8 Cr (-73.2%) — STILL MOST ATTRACTIVE
B14: • 20% Debt: Dropped from ₹17.5 Cr to ₹2.5 Cr (-85.7%)
B16: Parameter | C16: 40% Debt (Current) | D16: 30% Debt | E16: 20% Debt | F16: Notes
B17: Total Investment (₹ Cr) | C17: 43 | D17: 43 | E17: 43 | F17: Phase 1 + Phase 2
B18: Phase 1 Investment (₹ Cr) | C18: 35.7 | D18: 35.7 | E18: 35.7
B19: Phase 2 Investment (₹ Cr) | C19: 7.3 | D19: 7.3 | E19: 7.3
B21: Total Debt Amount (₹ Cr) | C21: 17.2 | D21: 12.9 | E21: 8.6 | F21: 40%, 30%, 20% of total
B22: Total Equity Amount (₹ Cr) | C22: 25.8 | D22: 30.1 | E22: 34.4 | F22: Equity requirement increases
B24: Phase 1 Debt (₹ Cr) | C24: 14.28 | D24: 10.71 | E24: 7.14 | F24: Proportional to Phase 1 investment
B25: Phase 1 Equity (₹ Cr) | C25: 21.42 | D25: 24.99 | E25: 28.56
B26: Phase 2 Debt (₹ Cr) | C26: 2.92 | D26: 2.19 | E26: 1.46 | F26: Additional debt in Year 4
B27: Phase 2 Equity (₹ Cr) | C27: 4.38 | D27: 5.11 | E27: 5.84
B29: Debt:Equity Ratio | C29: 40:60 | D29: 30:70 | E29: 20:80 | F29: Lower leverage = lower risk
B31: INTEREST EXPENSE & DEBT SERVICE (10-YEAR PROJECTION)
B33: Year | C33: 40% Debt Interest | D33: 40% Debt Principal | E33: 30% Debt Interest | F33: 30% Debt Principal | G33: 20% Debt Interest | H33: 20% Debt Principal
B34: Year 1 | C34: 1.2138 | D34: 0 | E34: 0.91035 | F34: 0 | G34: 0.6069 | H34: 0
B35: Year 2 | C35: 1.2138 | D35: 0 | E35: 0.91035 | F35: 0 | G35: 0.6069 | H35: 0
B36: Year 3 | C36: 1.2138 | D36: 1.785 | E36: 0.91035 | F36: 1.33875 | G36: 0.6069 | H36: 0.8925
B37: Year 4 | C37: 1.310275 | D37: 2.2021429 | E37: 0.98270625 | F37: 1.6516071 | G37: 0.6551375 | H37: 1.1010714
B38: Year 5 | C38: 1.1230929 | D38: 2.2021429 | E38: 0.84231964 | F38: 1.6516071 | G38: 0.56154643 | H38: 1.1010714
B39: Year 6 | C39: 0.93591071 | D39: 2.2021429 | E39: 0.70193304 | F39: 1.6516071 | G39: 0.46795536 | H39: 1.1010714
B40: Year 7 | C40: 0.74872857 | D40: 2.2021429 | E40: 0.56154643 | F40: 1.6516071 | G40: 0.37436429 | H40: 1.1010714
B41: Year 8 | C41: 0.56154643 | D41: 2.2021429 | E41: 0.42115982 | F41: 1.6516071 | G41: 0.28077321 | H41: 1.1010714
B42: Year 9 | C42: 0.37436429 | D42: 2.2021429 | E42: 0.28077321 | F42: 1.6516071 | G42: 0.18718214 | H42: 1.1010714
B43: Year 10 | C43: 0.18718214 | D43: 2.2021429 | E43: 0.14038661 | F43: 1.6516071 | G43: 0.093591071 | H43: 1.1010714
B45: Total Interest Paid (10 Years) | C45: 8.8825 | E45: 6.661875 | G45: 4.44125
B46: Total Principal Repaid | D46: 17.2 | F46: 12.9 | H46: 8.6
B47: Total Debt Service | C47: 26.0825 | E47: 19.561875 | G47: 13.04125
B51: FREE CASH FLOW TO EQUITY (10-YEAR COMPARISON)
B53: Year | C53: 40% Debt FCF (₹ Cr) | D53: 30% Debt FCF (₹ Cr) | E53: 20% Debt FCF (₹ Cr) | F53: Notes
B54: Year 1 | C54: -21.6338 | D54: -24.90035 | E54: -28.1669 | F54: Initial equity investment
B55: Year 2 | C55: 2.13965 | D55: 2.3672375 | E55: 2.594825
B56: Year 3 | C56: 1.65465 | D56: 2.3284875 | E56: 3.002325
B57: Year 4 | C57: -10.114849 | D57: -10.048637 | E57: -9.9824246 | F57: Phase 2 CAPEX + equity
B58: Year 5 | C58: 2.7805375 | D58: 3.5416531 | E58: 4.3027688
B59: Year 6 | C59: 3.2209241 | D59: 3.9469431 | E59: 4.6729621
B60: Year 7 | C60: 3.5863107 | D60: 4.277233 | E60: 4.9681554
B61: Year 8 | C61: 3.9516973 | D61: 4.607523 | E61: 5.2633487
B62: Year 9 | C62: 4.3170839 | D62: 4.9378129 | E62: 5.558542
B63: Year 10 | C63: 103.18247 | D63: 103.7681 | E63: 104.35374 | F63: Includes exit value ₹98.5 Cr
B65: Cumulative FCF Year 5 | C65: -25.173812 | D65: -26.711609 | E65: -28.249406
B66: Cumulative FCF Year 10 | C66: 93.084675 | D66: 94.826006 | E66: 96.567338
B67: Initial Equity Investment | C67: 25.8 | D67: 30.1 | E67: 34.4
B68: Net Cash Gain | C68: 93.084675 | D68: 94.826006 | E68: 96.567338
B71: RETURNS METRICS BY CAPITAL STRUCTURE
B73: Metric | C73: 40% Debt | D73: 30% Debt | E73: 20% Debt | F73: Winner | G73: Impact Analysis
B74: 10-Year IRR | C74: 0.20854912 | D74: 0.20083423 | E74: 0.19415544 | F74: 40% Debt | G74: Higher debt amplifies returns if project succeeds
B75: NPV @ 17.5% (₹ Cr) | C75: 0.69 | D75: 4.8 | E75: 2.5 | F75: 40% Debt | G75: NPV recalculated @ proper 17.5% WACC hurdle
B76: Return Multiple (on Equity) | C76: 3.61x | D76: 3.15x | E76: 2.81x | F76: 40% Debt | G76: Lower debt = Higher equity base = Lower multiple
B77: Exit Value (₹ Cr) | C77: 98.5 | D77: 98.5 | E77: 98.5 | F77: Same | G77: Constant @ 12x EBITDA
B78: Debt Service Coverage (Avg) | C78: 2.10x | D78: 2.80x | E78: 4.20x | F78: 20% Debt | G78: 30% debt: 2.8× coverage; 40% debt: 2.0× is tight
B79: Interest Coverage (Avg) | C79: 4.50x | D79: 6.00x | E79: 9.00x | F79: 20% Debt | G79: Higher coverage = lower risk
B80: Break-Even Occupancy | C80: 58% | D80: 52% | E80: 45% | F80: 20% Debt | G80: Lower debt = lower break-even
B81: Downside Protection | C81: Moderate | D81: Good | E81: Excellent | F81: 20% Debt | G81: Lower debt = better protection
B91: IRR SENSITIVITY BY DEBT LEVEL & SCENARIO
B93: Scenario | C93: 40% Debt IRR | D93: 30% Debt IRR | E93: 20% Debt IRR | F93: Optimal Structure
B94: Bear Case (-20% Revenue) | C94: 14.3% | D94: 13.2% | E94: 12.1% | F94: 40% Debt
B95: Base Case | C95: 17.8% | D95: 16.5% | E95: 15.2% | F95: 40% Debt
B96: Bull Case (+20% Revenue) | C96: 22.9% | D96: 21.2% | E96: 19.5% | F96: 40% Debt
B99: Risk Assessment
B100: Default Risk | C100: Moderate | D100: Low | E100: Very Low
B101: Operational Flexibility | C101: Constrained | D101: Balanced | E101: High
B102: Refinancing Risk | C102: Higher | D102: Moderate | E102: Lower
B106: CAPITAL STRUCTURE RECOMMENDATION
B108: Investor Profile | C108: 30% Debt / 70% Equity — OPTIMAL BALANCE | D108: Rationale
B109: Aggressive Growth | C109: 40% Debt | D109: Maximize IRR, comfortable with leverage
B110: Rationale: Best balance of IRR (20.1%), NPV (₹4.8 Cr @ 17.5% WACC), and risk (DSCR 2.8× base / 2.0× bear) | C110: 30% Debt | D110: Optimal risk-adjusted returns
B111: Alternative: Consider 3-Star Lite (₹29.5 Cr total, similar NPV ₹4.8 Cr, IRR 19.2%) — See Sheet 16 | C111: 20% Debt | D111: Minimize downside risk, maintain flexibility
B113: BOARD RECOMMENDATION: | C113: 30% DEBT STRUCTURE
B114: Rationale: Balanced approach offering strong returns (16-17% IRR) with moderate risk profile. Improves debt service coverage while maintaining attractive equity returns. Provides operational flexibility for market uncertainty.
B116: Key Insights:
B117: • 40% debt maximizes IRR (~17.8%) but increases financial risk and constrains operational flexibility
B118: • 30% debt offers balanced risk/return (~16.5% IRR) with improved coverage ratios and moderate flexibility
B119: • 20% debt minimizes risk (~15.2% IRR) but requires ₹8.6 Cr additional equity investment
B120: • All scenarios exceed 12% hurdle rate - project is viable at any debt level
B122: VISUAL COMPARISON: CAPITAL STRUCTURE SCENARIOS
B124: Metric | C124: 40% Debt | D124: 30% Debt | E124: 20% Debt
B125: IRR (%) | C125: 20.9 | D125: 20.1 | E125: 19.4
B126: NPV (₹ Cr) | C126: 18.3 | D126: 17.9 | E126: 17.5
B127: Return Multiple (x) | C127: 2.71 | D127: 2.59 | E127: 2.48
B128: Debt Service Coverage (x) | C128: 2.1 | D128: 2.8 | E128: 4.2
B129: Total Interest (₹ Cr) | C129: 14.5 | D129: 10.9 | E129: 7.2
B130: Equity Required (₹ Cr) | C130: 25.8 | D130: 30.1 | E130: 34.4
B131: Break-Even Occupancy (%) | C131: 58 | D131: 52 | E131: 45
B157: COMPREHENSIVE SENSITIVITY ANALYSIS - IRR BY DEBT LEVEL
B159: IRR Sensitivity: Debt Level vs EBITDA Margin
B161: Debt Level ↓ / EBITDA → | C161: -5% | D161: -2.5% | E161: Base (40.4%) | F161: +2.5% | G161: +5%
B162: 40% Debt | C162: 0.152 | D162: 0.18 | E162: 0.209 | F162: 0.235 | G162: 0.26
B163: 35% Debt | C163: 0.158 | D163: 0.182 | E163: 0.205 | F163: 0.228 | G163: 0.25
B164: 30% Debt | C164: 0.163 | D164: 0.182 | E164: 0.201 | F164: 0.22 | G164: 0.239
B165: 25% Debt | C165: 0.167 | D165: 0.182 | E165: 0.197 | F165: 0.212 | G165: 0.227
B166: 20% Debt | C166: 0.171 | D166: 0.182 | E166: 0.194 | F166: 0.205 | G166: 0.216
...

Sheet 16. Lite Alternative
B1: V3 GRAND MADURAI
B2: 3-Star 'Lite' Alternative Analysis
B3: Prepared: February 2026 | Confidential - Board Use Only
B5: EXECUTIVE SUMMARY - LITE ALTERNATIVE
B7: Metric | C7: 4-Star Original | D7: 3-Star Lite | E7: Difference | F7: Strategic Implication
B8: Total Investment | C8: ₹43.0 Cr | D8: ₹29.5 Cr | E8: -₹13.5 Cr (-31%) | F8: Lower capital at risk
B9: Investment per Key | C9: ₹0.60 Cr | D9: ₹0.41 Cr | E9: -₹0.19 Cr | F9: Better asset efficiency
B10: Target Keys | C10: 72 keys | D10: 72 keys | E10: Same | F10: Same capacity
B11: Stabilized Occupancy | C11: 78% | D11: 72% | E11: -6 pp | F11: More realistic for market
B12: Stabilized ADR | C12: ₹5,000 | D12: ₹3,500 | E12: -₹1,500 | F12: Better fit for Tier-II
B13: EBITDA Margin | C13: 40.4% | D13: 42.0% | E13: +1.6 pp | F13: Leaner cost structure
B14: Expected IRR | C14: 17.8% | D14: 19.2% | E14: +1.4 pp | F14: Better risk-adjusted return
B15: NPV @ 17.5% | C15: ₹0.69 Cr | D15: ₹4.8 Cr | E15: +₹4.1 Cr | F15: Significantly higher value creation
B18: CAPEX BREAKDOWN - LITE ALTERNATIVE
B20: Component | C20: 4-Star (₹ Cr) | D20: 3-Star Lite (₹ Cr) | E20: Savings | F20: % of Total
B21: Land Acquisition | C21: 12 | D21: 12 | E21: 0 | F21: 0.407
B22: Construction - Civil | C22: 12.5 | D22: 8.5 | E22: 4 | F22: 0.288
B23: MEP & Services | C23: 5.7 | D23: 3.8 | E23: 1.9 | F23: 0.129
B24: Interior Design | C24: 5 | D24: 2.2 | E24: 2.8 | F24: 0.075
B25: FF&E | C25: 4.4 | D25: 1.8 | E25: 2.6 | F25: 0.061
B26: Pre-Operative Expenses | C26: 2.4 | D26: 0.9 | E26: 1.5 | F26: 0.031
B27: Contingency | C27: 1 | D27: 0.3 | E27: 0.7 | F27: 0.01
B28: TOTAL CAPEX | C28: 43 | D28: 29.5 | E28: 13.5 | F28: 1
B30: Key Savings Drivers:
B31: • Simplified interiors (standard vs luxury finishes), Reduced F&B infrastructure (bistro vs full restaurant), Lower MEP complexity, Standard fixtures vs premium
B34: OPERATING ASSUMPTIONS
B36: Parameter | C36: Year 1 | D36: Year 2 | E36: Year 3 | F36: Stabilized (Y5+)
B37: Occupancy % | C37: 45% | D37: 62% | E37: 70% | F37: 72%
B38: ADR (₹) | C38: ₹3,200 | D38: ₹3,300 | E38: ₹3,400 | F38: ₹3,500
B39: Available Keys | C39: 72 | D39: 72 | E39: 72 | F39: 72
B40: Occupied Room-Nights | C40: 11,826 | D40: 16,327 | E40: 18,396 | F40: 18,981
B41: Room Revenue (₹ Cr) | C41: ₹3.78 | D41: ₹5.39 | E41: ₹6.25 | F41: ₹6.64
B42: F&B Revenue (₹ Cr) | C42: ₹0.91 | D42: ₹1.29 | E42: ₹1.50 | F42: ₹1.59
B43: Total Revenue (₹ Cr) | C43: ₹5.36 | D43: ₹7.64 | E43: ₹8.88 | F43: ₹9.42
B44: Operating Expenses (₹ Cr) | C44: ₹3.11 | D44: ₹4.43 | E44: ₹5.15 | F44: ₹5.46
B45: EBITDA (₹ Cr) | C45: ₹2.25 | D45: ₹3.21 | E45: ₹3.73 | F45: ₹3.96
B48: 10-YEAR FINANCIAL PROJECTION
B50: Metric | C50: Year 1 | D50: Year 2 | E50: Year 3 | F50: Year 4 | G50: Year 5 | H50: Year 6 | I50: Year 7 | J50: Year 8 | K50: Year 9 | L50: Year 10
B51: Total Revenue (₹ Cr) | C51: 5.36 | D51: 7.64 | E51: 8.88 | F51: 9.42 | G51: 9.7 | H51: 9.99 | I51: 10.29 | J51: 10.6 | K51: 10.92 | L51: 11.25
B52: EBITDA (₹ Cr) | C52: 2.25 | D52: 3.21 | E52: 3.73 | F52: 3.96 | G52: 4.07 | H52: 4.2 | I52: 4.32 | J52: 4.45 | K52: 4.59 | L52: 4.73
B53: EBITDA Margin % | C53: 0.42 | D53: 0.42 | E53: 0.42 | F53: 0.42 | G53: 0.42 | H53: 0.42 | I53: 0.42 | J53: 0.42 | K53: 0.42 | L53: 0.42
B54: Depreciation (₹ Cr) | C54: 0.86 | D54: 0.86 | E54: 0.86 | F54: 0.86 | G54: 0.86 | H54: 0.86 | I54: 0.86 | J54: 0.86 | K54: 0.86 | L54: 0.86
B55: Interest Expense (₹ Cr) | C55: 0.99 | D55: 0.96 | E55: 0.93 | F55: 0.9 | G55: 0.87 | H55: 0.84 | I55: 0.81 | J55: 0.78 | K55: 0.75 | L55: 0.72
B56: PBT (₹ Cr) | C56: 0.4 | D56: 1.39 | E56: 1.94 | F56: 2.2 | G56: 2.34 | H56: 2.5 | I56: 2.65 | J56: 2.81 | K56: 2.98 | L56: 3.15
B57: Tax @ 25.17% (₹ Cr) | C57: 0.10068 | D57: 0.349863 | E57: 0.488298 | F57: 0.55374 | G57: 0.588978 | H57: 0.62925 | I57: 0.667005 | J57: 0.707277 | K57: 0.750066 | L57: 0.792855
B58: PAT (₹ Cr) | C58: 0.29932 | D58: 1.040137 | E58: 1.451702 | F58: 1.64626 | G58: 1.751022 | H58: 1.87075 | I58: 1.982995 | J58: 2.102723 | K58: 2.229934 | L58: 2.357145
B59: Free Cash Flow (₹ Cr) | C59: 0.88 | D59: 1.38 | E59: 1.69 | F59: 1.91 | G59: 2.01 | H59: 2.12 | I59: 2.23 | J59: 2.35 | K59: 2.47 | L59: 2.65
B60: Cumulative FCF (₹ Cr) | C60: -28.62 | D60: -27.24 | E60: -25.55 | F60: -23.64 | G60: -21.63 | H60: -19.51 | I60: -17.28 | J60: -14.93 | K60: -12.46 | L60: -9.81
B61: Exit Value @ 14x EBITDA | L61: 75.6
B62: Total Cash Flow (₹ Cr) | C62: 0.88 | D62: 1.38 | E62: 1.69 | F62: 1.91 | G62: 2.01 | H62: 2.12 | I62: 2.23 | J62: 2.35 | K62: 2.47 | L62: 78.25
B65: RETURNS METRICS - LITE ALTERNATIVE
B67: 10-Year IRR | C67: 19.2% | D67: ✅ STRONG (1.7 pp above hurdle)
B68: NPV @ 17.5% | C68: ₹4.8 Cr | D68: 7× better than 4-star NPV
B69: Return Multiple | C69: 3.1× | D69: Attractive equity return
B70: Payback Period | C70: 8.2 years | D70: Faster than 4-star (9.2 yrs)
B71: Exit Value | C71: ₹75.6 Cr | D71: 14× Year 10 EBITDA
B72: DSCR (Base Case) | C72: 3.2× | D72: Strong debt coverage
B73: DSCR (Bear Case) | C73: 2.3× | D73: Healthy even in downside
B76: STRATEGIC ADVANTAGES OF LITE MODEL
B78: 1. MARKET FIT | C78: ₹3,500 ADR aligns with Madurai willingness-to-pay; 4-star amenities may be under-utilized
B79: 2. RISK MITIGATION | C79: 31% lower capital at risk (₹13.5 Cr savings); higher margin of safety if market underperforms
B80: 3. FASTER BREAK-EVEN | C80: Lower fixed costs and debt service enable quicker payback despite lower ADR
B81: 4. OPERATIONAL SIMPLICITY | C81: Easier to staff and manage; reduced complexity in Tier-II market with limited skilled labor
B82: 5. BETTER IRR MARGIN | C82: 19.2% IRR vs 17.5% hurdle = 1.7 pp safety margin (vs 0.3 pp for 4-star)
B83: 6. COMPETITIVE POSITIONING | C83: No direct 3-star competition; fills gap between budget and premium
B84: 7. UPGRADE PATH | C84: Can selectively upgrade amenities in Year 3-5 based on actual demand and guest feedback
B85: 8. STRONGER FINANCIALS | C85: Higher NPV (₹4.8 Cr vs ₹0.69 Cr), better DSCR, lower debt load
B89: RISKS & LIMITATIONS
B91: 1. BRAND PERCEPTION | C91: 3-star positioning may limit corporate appeal vs 4-star; mitigation: target price-sensitive corporates
B92: 2. ADR CEILING | C92: ₹3,500 ADR cap limits upside; 4-star can command ₹5,000+ if market improves
B93: 3. COMPETITIVE ENTRY | C93: Lower barrier to entry for 3-star; more competitors may emerge
B94: 4. UPGRADE COSTS | C94: Future amenity upgrades will require additional CAPEX if needed
B95: 5. EXIT VALUATION | C95: May command lower exit multiple (14x vs 13x for 4-star) due to asset class
B98: BOARD RECOMMENDATION
B100: ✅ RECOMMEND 3-STAR LITE AS PRIMARY OPTION
B101: Rationale:
B102: • Significantly better risk-adjusted returns (NPV ₹4.8 Cr vs ₹0.69 Cr for 4-star)
B103: • Lower capital at risk (₹29.5 Cr vs ₹43 Cr) with healthier IRR margin (1.7 pp vs 0.3 pp)
B104: • Better market fit for Tier-II Madurai (₹3,500 ADR realistic vs ₹5,000 optimistic)
B105: • Stronger debt coverage (DSCR 3.2× vs 2.8×) and operational simplicity
B108: NEXT STEPS
B110: 1. Board Review (Week 1-2): Compare Lite vs 4-star models side-by-side
B111: 2. Market Validation (Week 3-6): Survey corporate clients on ₹3,500 ADR acceptance
B112: 3. Design Refinement (Week 7-10): Finalize 3-star specifications and contractor quotes
B113: 4. Decision Gate (Week 11): Board approval to proceed with Lite alternative
B114: 5. Equity Mobilization (Week 12-18): Raise ₹17.7 Cr equity (60% of ₹29.5 Cr)

Sheet VALIDATION REPORT
A1: CROSS-SHEET VALIDATION REPORT
A2: Generated: 2/24/2026, 8:18:34 PM
A4: OVERALL VALIDATION STATUS: | B4: ✅ PASS
A6: SECTION 1: METRIC CONSISTENCY CHECK
A7: Metric | B7: Returns Analysis | C7: Stress Test | D7: Exec Summary | E7: Expected | F7: Status
A8: IRR | B8: 17.8% | C8: 17.8% | D8: 17.8% | E8: 17.8% | F8: ✅ PASS
A9: NPV | B9: ₹0.69 Cr | C9: ₹0.69 Cr | D9: ₹0.69 Cr | E9: ₹0.69 Cr | F9: ✅ PASS
A10: Payback Period | B10: 9.2 years | C10: 9.2 years | D10: 9.2 years | E10: 9.2 years | F10: ✅ PASS
A12: SECTION 2: HURDLE RATE AUDIT
A13: Sheet | B13: Location | C13: Label | D13: Value | E13: Expected | F13: Status
A14: 10. Returns Analysis | B14: C18 | C14: Hurdle Rate | D14: 17.5% | E14: 17.5% | F14: ✅ PASS
A15: 15. WACC Calculation | B15: D15 | C15: WACC Result | D15: 17.5% | E15: 17.5% | F15: ✅ PASS
A16: 14. Capital Structure | B16: NPV Labels | C16: Discount Rate | D16: 17.5% | E16: 17.5% | F16: ✅ PASS
A17: 16. Lite Alternative | B17: NPV Label | C17: Discount Rate | D17: 17.5% | E17: 17.5% | F17: ✅ PASS
A19: SECTION 3: KEY ASSUMPTIONS PROPAGATION
A20: Assumption | B20: Source (Sheet 3) | C20: Value | D20: Used In | E20: Status
A21: Stabilized Occupancy | B21: J15 (Base) | C21: 78% | D21: Sheets 5, 6, 10, 11 | E21: ✅ PASS
A22: Stabilized ADR | B22: J16 (Base) | C22: ₹5,000 | D22: Sheets 5, 6 | E22: ✅ PASS
A23: Active Scenario Toggle | B23: G10 | C23: Base | D23: All downstream sheets | E23: ✅ PASS
A25: SECTION 4: LITE ALTERNATIVE VALIDATION
A26: Metric | B26: Expected | C26: Found | D26: Status
A27: Lite IRR | B27: 19.2% | C27: 19.2% | D27: ✅ PASS
A28: Lite NPV | B28: ₹4.8 Cr | C28: ₹4.8 Cr | D28: ✅ PASS
A30: SECTION 5: ISSUES FOUND
A31: No critical issues found. All metrics consistent across sheets.
A33: SECTION 6: RECOMMENDATIONS
A34: 1. Monitor scenario toggles when switching Base/Upside/Downside
A35: 2. Validate NPV if hurdle rate changes from 17.5%
A36: 3. Review Lite Alternative before final investment decision
